Workbook
Name ADHESIVOS_Solventes: BD!$B$8:$B$20
Name AdheySol: BD!$B$7
Name Aux_Med: BD!$B$216
Name CATEGORIAS: Listas!$M$2:$M$12
Name Cuer_: BD!$B$613
Name CUERO: BD!$B$614:$B$638
Name Destinación: Listas!$D$3:$D$8
Name Forma_: BD!$B$61
Name FORMACION: BD!$B$62:$B$169
Name Herraj_: BD!$B$659
Name HERRAJES: BD!$B$660:$B$1101
Name Herram_: BD!$B$1276
Name HERRAMIENTAS_: Tabla13[Material]
Name INSUMOS_COMPL_: BD!$B$1333:$B$1374
Name Intructores: Listas!$H$2:$H$31
Name Materiales: BD!$B$6:$B$1596
Name Observaciones: Listas!$K$2:$K$12
Name Papel_: BD!$B$1417
Name PAPELERIA_P: Tabla34[Material]
Name Programas: Listas!$F$2:$F$12
Name quimic_: BD!$B$1511
Name QUÍMICOS: BD!$B$1512:$B$1597
Name SECUNDARIO_MEDULAR: BD!$B$217:$B$430
Name Sin_Tex: BD!$B$1108
Name SiNTETICOS_TEXTILES: BD!$B$1109:$B$1151
Name SUELAS: BD!$B$1169:$B$1230
Name T_comp_Aux_AD: BD!$A$8:$J$20
Name Tabla_Completa: BD!$A$6:'BD'!$J$1596
Name Total_AdhySol: BD!$B$6
Name Total_Cuero: BD!$B$612
Name Total_Herrajes: BD!$B$658
Name Total_Herramientas: BD!$B$1275
Name Total_Ins_Compl: BD!$B$1331
Name Total_SECUNDARIO_MEDULAR: BD!$B$215
Name Total_Sint_y_Tex: BD!$B$1107
Name Total_Suelas: BD!$B$1167
Name Unidades: Listas!$B$3:$B$28

Sheet Soli_citud 
C1: CÓDIGO ÚNICO DE PEDIDO | F1: =IF(E2="","",CONCATENATE(LEFT(E2,1),MID(E2,SEARCH(" ",E2)+1,1),TEXT(O1,"DD"),TEXT(O1,"MM"),"-",IF(K1="",1,K1))) -> CH0706-3 | I1: Pedido # | K1: 3 | L1: FECHA DE ELABORACION | O1: 45450 | S1: Imagen del Producto
C2: INSTRUCTOR ENCARGADO | E2: Carlos Hincapie Monsalve | L2: CÉDULA | O2: =IFERROR(IF(E2="","",INDEX(Listas!H2:I30,MATCH('Soli_citud '!E2,Intructores,0),2)),"") -> 1036620040
C3: PROGRAMA | E3: COMPLEMENTARIO MARROQUINERIA | L3: FICHA(#) | O3: 3
A4: NOMBRE DEL PRODUCTO | D4: BOLSO CAMPESENA | L4: Destinación específica | O4: campesena
A5: VALOR DE UNA UNIDAD ($) | D5: =IF(K5="","",(SUM(W10:Y28)-(SUMIF(U10:V28,"Restar_Pedido",W10:Y28)))/$K$5) -> 11427.012 | G5: CANTIDAD A PRODUCIR | K5: 25 | M5: VALOR PRODUCCION($) | O5: =IFERROR(IF(K5=0,"",D5*K5),"") -> 285675.29
A7: Categoria del Insumo | D7: MATERIALES E INSUMOS. | O7: UNIDAD DE MEDIDA | Q7: CANTIDAD PEDIDA para: Un solo producto
S8: Ayuda de Cálculo | V8: =IF(K5="","",1/K5) -> 0.04 | Y8: =IFERROR((V8*X8)," ") -> 0
S9: Entregar | U9: Observaciones | W9: Valor materiales (S)
A10: SiNTETICOS_TEXTILES | D10: SINTETICO REF ARSENAL | O10: =IFERROR(IF(D10="","",INDEX(Tabla_Completa,MATCH(D10,Materiales,0),6)),"") -> cm2 | Q10: 1950 | S10: =IFERROR(IF(Q10="Unidad","1",(Q10*$K$5)),"") -> 48750 | U10: Negro | W10: =IFERROR(IF(D10="","",INDEX(Tabla_Completa,MATCH('Soli_citud '!D10,Materiales,0),7)*S10),"") -> 30539.554
A11: SiNTETICOS_TEXTILES | D11: SINTETICO REF ARSENAL | O11: =IFERROR(IF(D11="","",INDEX(Tabla_Completa,MATCH(D11,Materiales,0),6)),"") -> cm2 | Q11: 1300 | S11: =IFERROR(IF(Q11="Unidad","1",(Q11*$K$5)),"") -> 32500 | U11: gris | W11: =IFERROR(IF(D11="","",INDEX(Tabla_Completa,MATCH('Soli_citud '!D11,Materiales,0),7)*S11),"") -> 20359.702
A12: SECUNDARIO_MEDULAR | D12: CREMALLERA POLIÉSTER #6 | O12: =IFERROR(IF(D12="","",INDEX(Tabla_Completa,MATCH(D12,Materiales,0),6)),"") -> cm | Q12: 45 | S12: =IFERROR(IF(Q12="Unidad","1",(Q12*$K$5)),"") -> 1125 | U12: Negro | W12: =IFERROR(IF(D12="","",INDEX(Tabla_Completa,MATCH('Soli_citud '!D12,Materiales,0),7)*S12),"") -> 13758.75
A13: HERRAJES | D13: LLAVE METÁLICA DESLIZADOR #6 PARA CREMALLERA - NÍQUEL | O13: =IFERROR(IF(D13="","",INDEX(Tabla_Completa,MATCH(D13,Materiales,0),6)),"") -> U | Q13: 2 | S13: =IFERROR(IF(Q13="Unidad","1",(Q13*$K$5)),"") -> 50 | W13: =IFERROR(IF(D13="","",INDEX(Tabla_Completa,MATCH('Soli_citud '!D13,Materiales,0),7)*S13),"") -> 22783.312
A14: SECUNDARIO_MEDULAR | D14: CINTA FALLA _RIBETE 24 mm CON APRESTO #5 | O14: =IFERROR(IF(D14="","",INDEX(Tabla_Completa,MATCH(D14,Materiales,0),6)),"") -> m | Q14: 0.9 | S14: =IFERROR(IF(Q14="Unidad","1",(Q14*$K$5)),"") -> 22.5 | W14: =IFERROR(IF(D14="","",INDEX(Tabla_Completa,MATCH('Soli_citud '!D14,Materiales,0),7)*S14),"") -> 13162.5
A15: SECUNDARIO_MEDULAR | D15: CORDON TRENZADO ENCERADO VERDE _ CARRETE | O15: =IFERROR(IF(D15="","",INDEX(Tabla_Completa,MATCH(D15,Materiales,0),6)),"") -> cm | Q15: 125 | S15: =IFERROR(IF(Q15="Unidad","1",(Q15*$K$5)),"") -> 3125 | U15: carrete por 250 mts ap | W15: =IFERROR(IF(D15="","",INDEX(Tabla_Completa,MATCH('Soli_citud '!D15,Materiales,0),7)*S15),"")
A16: ADHESIVOS_Solventes | D16: PEGANTE CEMENTO DE CONTACTO BASE CLOROPRENO | O16: =IFERROR(IF(D16="","",INDEX(Tabla_Completa,MATCH(D16,Materiales,0),6)),"") -> ml | Q16: 144 | S16: =IFERROR(IF(Q16="Unidad","1",(Q16*$K$5)),"") -> 3600 | W16: =IFERROR(IF(D16="","",INDEX(Tabla_Completa,MATCH('Soli_citud '!D16,Materiales,0),7)*S16),"") -> 62876.83
A17: SiNTETICOS_TEXTILES | D17: SEDA ANTIFLUIDO, VARIOS COLORES | O17: =IFERROR(IF(D17="","",INDEX(Tabla_Completa,MATCH(D17,Materiales,0),6)),"") -> cm2 | Q17: 2500 | S17: =IFERROR(IF(Q17="Unidad","1",(Q17*$K$5)),"") -> 62500 | W17: =IFERROR(IF(D17="","",INDEX(Tabla_Completa,MATCH('Soli_citud '!D17,Materiales,0),7)*S17),"") -> 74069.643
A18: SECUNDARIO_MEDULAR | D18: YUMBOLON 4mm (CM²) | O18: =IFERROR(IF(D18="","",INDEX(Tabla_Completa,MATCH(D18,Materiales,0),6)),"") -> cm2 | Q18: 2500 | S18: =IFERROR(IF(Q18="Unidad","1",(Q18*$K$5)),"") -> 62500 | W18: =IFERROR(IF(D18="","",INDEX(Tabla_Completa,MATCH('Soli_citud '!D18,Materiales,0),7)*S18),"") -> 48125
A19: INSUMOS_COMPL_ | D19: CARTULINA PLANA | O19: =IFERROR(IF(D19="","",INDEX(Tabla_Completa,MATCH(D19,Materiales,0),6)),"") -> Pliego | Q19: 1.3 | S19: =IFERROR(IF(Q19="Unidad","1",(Q19*$K$5)),"") -> 32.5 | W19: =IFERROR(IF(D19="","",INDEX(Tabla_Completa,MATCH('Soli_citud '!D19,Materiales,0),7)*S19),"")
O20: =IFERROR(IF(D20="","",INDEX(Tabla_Completa,MATCH(D20,Materiales,0),6)),"") | S20: =IFERROR(IF(Q20="Unidad","1",(Q20*$K$5)),"") -> 0 | W20: =IFERROR(IF(D20="","",INDEX(Tabla_Completa,MATCH('Soli_citud '!D20,Materiales,0),7)*S20),"")
O21: =IFERROR(IF(D21="","",INDEX(Tabla_Completa,MATCH(D21,Materiales,0),6)),"") | S21: =IFERROR(IF(Q21="Unidad","1",(Q21*$K$5)),"") -> 0 | W21: =IFERROR(IF(D21="","",INDEX(Tabla_Completa,MATCH('Soli_citud '!D21,Materiales,0),7)*S21),"")
O22: =IFERROR(IF(D22="","",INDEX(Tabla_Completa,MATCH(D22,Materiales,0),6)),"") | S22: =IFERROR(IF(Q22="Unidad","1",(Q22*$K$5)),"") -> 0 | W22: =IFERROR(IF(D22="","",INDEX(Tabla_Completa,MATCH('Soli_citud '!D22,Materiales,0),7)*S22),"")
O23: =IFERROR(IF(D23="","",INDEX(Tabla_Completa,MATCH(D23,Materiales,0),6)),"") | S23: =IFERROR(IF(Q23="Unidad","1",(Q23*$K$5)),"") -> 0 | W23: =IFERROR(IF(D23="","",INDEX(Tabla_Completa,MATCH('Soli_citud '!D23,Materiales,0),7)*S23),"")
O24: =IFERROR(IF(D24="","",INDEX(Tabla_Completa,MATCH(D24,Materiales,0),6)),"") | S24: =IFERROR(IF(Q24="Unidad","1",(Q24*$K$5)),"") -> 0 | W24: =IFERROR(IF(D24="","",INDEX(Tabla_Completa,MATCH('Soli_citud '!D24,Materiales,0),7)*S24),"")
O25: =IFERROR(IF(D25="","",INDEX(Tabla_Completa,MATCH(D25,Materiales,0),6)),"") | S25: =IFERROR(IF(Q25="Unidad","1",(Q25*$K$5)),"") -> 0 | W25: =IFERROR(IF(D25="","",INDEX(Tabla_Completa,MATCH('Soli_citud '!D25,Materiales,0),7)*S25),"")
O26: =IFERROR(IF(D26="","",INDEX(Tabla_Completa,MATCH(D26,Materiales,0),6)),"") | S26: =IFERROR(IF(Q26="Unidad","1",(Q26*$K$5)),"") -> 0 | W26: =IFERROR(IF(D26="","",INDEX(Tabla_Completa,MATCH('Soli_citud '!D26,Materiales,0),7)*S26),"")
O27: =IFERROR(IF(D27="","",INDEX(Tabla_Completa,MATCH(D27,Materiales,0),6)),"") | S27: =IFERROR(IF(Q27="Unidad","1",(Q27*$K$5)),"") -> 0 | W27: =IFERROR(IF(D27="","",INDEX(Tabla_Completa,MATCH('Soli_citud '!D27,Materiales,0),7)*S27),"")
O28: =IFERROR(IF(D28="","",INDEX(Tabla_Completa,MATCH(D28,Materiales,0),6)),"") | S28: =IFERROR(IF(Q28="Unidad","1",(Q28*$K$5)),"") -> 0 | W28: =IFERROR(IF(D28="","",INDEX(Tabla_Completa,MATCH('Soli_citud '!D28,Materiales,0),7)*S28),"")
O29: =IFERROR(IF(D29="","",INDEX(Tabla_Completa,MATCH(D29,Materiales,0),6)),"") | S29: =IFERROR(IF(Q29="Unidad","1",(Q29*$K$5)),"") -> 0 | W29: =IFERROR(IF(D29="","",INDEX(Tabla_Completa,MATCH('Soli_citud '!D29,Materiales,0),7)*S29),"")
O30: =IFERROR(IF(D30="","",INDEX(Tabla_Completa,MATCH(D30,Materiales,0),6)),"") | S30: =IFERROR(IF(Q30="Unidad","1",(Q30*$K$5)),"") -> 0 | W30: =IFERROR(IF(D30="","",INDEX(Tabla_Completa,MATCH('Soli_citud '!D30,Materiales,0),7)*S30),"")
O31: =IFERROR(IF(D31="","",INDEX(Tabla_Completa,MATCH(D31,Materiales,0),6)),"") | S31: =IFERROR(IF(Q31="Unidad","1",(Q31*$K$5)),"") -> 0 | W31: =IFERROR(IF(D31="","",INDEX(Tabla_Completa,MATCH('Soli_citud '!D31,Materiales,0),7)*S31),"")
A39: Recomendación: | D39: Descargar el archivo en aplicación de escritorio, para un mejor funcionamiento!! Mantener el archivo de One Drive, como "Original para copia"
A40: Insertar Imagen: en la ruta: Insertar/Ilustraciones/Imágenes/en este dispositivo
A44: Instrucciones Generales | N44: ADHESIVOS_Solventes | R44: Todo lo relacionado con adhesivos, incluido los solventes
A45: Los campos en color naranja son obligatorios, se deben registrar | N45: SECUND_MEDULAR | R45: Todos los insumos que hacen parte del producto, en un nivel secundario, o que van en la parte interna de los productos
A46: Los campos de este color en la parte de debajo o a un lado significa que tiene una lista desplegable | N46: CUERO | R46: Solo insumos bajo esta categoría
A47: Los campos en color gris oscuro y claro,son campos que no permiten edición( estan Bloqueados) | N47: HERRAJES | R47: Todos los insumos que cumplen esta condición
A48: Para ingresar la fecha, solo digite asi: tecla CTRL + tecla de punto y coma(;) | N48: HERRAMIENTAS | R48: Todos los elementos necesarios para desarrollar el proceso, estos no deben hacer parte del costo
A49: Leer cada una de las casillas con notas, como ayuda para el correcto llenado de datos | N49: INSUMOS_COMPlementarios | R49: Todos los insumos necesarios en elproceso del producto pero que no quedan dentro del producto ( ejm Agujas)
N50: PAPELERIA_P | R50: Todos los elementos que cumplen esta condición
N51: SiNTETICOS_TEXTILES | R51: Todos los insumos utilizados altenativos al cuero o forro
N52: SUELAS | R52: Todos los insumos que cumplen esta condición

Sheet Entrega de Pedido
D1: SERVICIO NACIONAL DE APRENDIZAJE SENA FORMATO DE SOLICITUD DE SALIDA DE INSUMOS ALMACEN MATERIALES CDMC | J1: FECHA SOLICITUD | N1: =IF('Soli_citud '!O1="","",'Soli_citud '!O1) -> 45450 | P1: Foto | R1: =IF('Soli_citud '!D4="","",'Soli_citud '!D4) -> BOLSO CAMPESENA | Z1: Pete | AA1: Pete
J2: CODIGO ASIGNADO | N2: ='Soli_citud '!F1 -> CH0706-3
J3: FICHA DE CARACTERIZACIÓN | N3: =IF('Soli_citud '!O3="","",'Soli_citud '!O3) -> 3 | R3: {=IFERROR(_xlfn.IFS(L4="Calzado Producción","Entrega de Producto",L4="Marroquinería Producción","Entrega Producto"),"")}
J4: DESTINACIÓN DEL PEDIDO | M4: =IF('Soli_citud '!O4="","",'Soli_citud '!O4) -> campesena
B6: VALOR DE UNA UNIDAD DE PRODUCTO | E6: COORDINADOR DE LA LINEA MEDULAR: | R6: =IF(R3="","","Valor de Producción ($)")
R7: =IFERROR(IF(R3="","",G9*M10),"")
B8: =IF('Soli_citud '!D5<= 0,"",'Soli_citud '!D5) -> 11427.012 | E8: INSTRUCTOR QUE SOLICITA EL PEDIDO: | J8: =IF('Soli_citud '!E2="","",'Soli_citud '!E2) -> Carlos Hincapie Monsalve
B9: INCREMENTO DEL VALOR (%) | E9: VALOR APROBADO | G9: =IFERROR(IF(D9="","",ROUNDUP(B8*(1+D9),-2)),"")
J10: Productos a Realizar /entregar | M10: =IF('Soli_citud '!K5="","",'Soli_citud '!K5) -> 25 | N10: Entrega de material | R10: Total Entregado | S10: {=IFERROR(_xlfn.IFS(M10=1,"",M10>SUM(S12:S30),SUM(S12:S30),M10=SUM(S12:S30),"Cumplido",M10<SUM(S12:S30),"Revisar"),"")} -> 0
A11: Item | B11: Codigo solicitud | C11: DESCRIPCION DE BIEN | G11: UNIDA DE MEDIDA | H11: CANTIDAD SOLICITADA | I11: Fecha Entrega | J11: CANTIDAD Entregada 1 | K11: Faltante por entregar | L11: Observaciones | N11: Ancho del material (cm) | O11: Entrega Lineal material (cm) | P11: Devolutivo | Q11: Fecha Recibo | R11: Fecha Recibo | S11: CANTIDAD Recibido
A12: 1 | B12: =IF(H12="","",$N$2) -> CH0706-3 | C12: =IFERROR(IF('Soli_citud '!D10="","",'Soli_citud '!D10),"") -> SINTETICO REF ARSENAL | G12: =IF('Soli_citud '!O10="","",'Soli_citud '!O10) -> cm2 | H12: {=_xlfn.IFS('Soli_citud '!S10="","",'Soli_citud '!S10<=0,"",'Soli_citud '!S10>0,'Soli_citud '!S10)} -> 48750 | I12: 45456 | J12: 48750 | K12: {=IFERROR(_xlfn.IFS(H12="","",J12=H12,"Cumplido",J12<H12,H12-J12,J12>H12,"Revisar"),"")} -> Cumplido | N12: 140 | O12: =IFERROR(H12/N12,"") -> 348.21429 | P12: {=IFERROR(_xlfn.IFS(Q12>0,"ENTREGADO",'Soli_citud '!A10="HERRAMIENTAS_","DEVOLUTIVO"),"")}
A13: 2 | B13: =IF(H13="","",$N$2) -> CH0706-3 | C13: =IFERROR(IF('Soli_citud '!D11="","",'Soli_citud '!D11),"") -> SINTETICO REF ARSENAL | G13: =IF('Soli_citud '!O11="","",'Soli_citud '!O11) -> cm2 | H13: {=_xlfn.IFS('Soli_citud '!S11="","",'Soli_citud '!S11<=0,"",'Soli_citud '!S11>0,'Soli_citud '!S11)} -> 32500 | I13: 45456 | J13: 32500 | K13: {=IFERROR(_xlfn.IFS(H13="","",J13=H13,"Cumplido",J13<H13,H13-J13,J13>H13,"Revisar"),"")} -> Cumplido | N13: 140 | O13: =IFERROR(H13/N13,"") -> 232.14286 | P13: {=IFERROR(_xlfn.IFS(Q13>0,"ENTREGADO",'Soli_citud '!A11="HERRAMIENTAS_","DEVOLUTIVO"),"")}
A14: 3 | B14: =IF(H14="","",$N$2) -> CH0706-3 | C14: =IFERROR(IF('Soli_citud '!D12="","",'Soli_citud '!D12),"") -> CREMALLERA POLIÉSTER #6 | G14: =IF('Soli_citud '!O12="","",'Soli_citud '!O12) -> cm | H14: {=_xlfn.IFS('Soli_citud '!S12="","",'Soli_citud '!S12<=0,"",'Soli_citud '!S12>0,'Soli_citud '!S12)} -> 1125 | I14: 45456 | J14: 1125 | K14: {=IFERROR(_xlfn.IFS(H14="","",J14=H14,"Cumplido",J14<H14,H14-J14,J14>H14,"Revisar"),"")} -> Cumplido | N14: 100 | O14: =IFERROR(H14/N14,"") -> 11.25 | P14: {=IFERROR(_xlfn.IFS(Q14>0,"ENTREGADO",'Soli_citud '!A12="HERRAMIENTAS_","DEVOLUTIVO"),"")}
A15: 4 | B15: =IF(H15="","",$N$2) -> CH0706-3 | C15: =IFERROR(IF('Soli_citud '!D13="","",'Soli_citud '!D13),"") -> LLAVE METÁLICA DESLIZADOR #6 PARA CREMALLERA - NÍQUEL | G15: =IF('Soli_citud '!O13="","",'Soli_citud '!O13) -> U | H15: {=_xlfn.IFS('Soli_citud '!S13="","",'Soli_citud '!S13<=0,"",'Soli_citud '!S13>0,'Soli_citud '!S13)} -> 50 | I15: 45456 | J15: 50 | K15: {=IFERROR(_xlfn.IFS(H15="","",J15=H15,"Cumplido",J15<H15,H15-J15,J15>H15,"Revisar"),"")} -> Cumplido | N15: 1 | O15: =IFERROR(H15/N15,"") -> 50 | P15: {=IFERROR(_xlfn.IFS(Q15>0,"ENTREGADO",'Soli_citud '!A13="HERRAMIENTAS_","DEVOLUTIVO"),"")}
A16: 5 | B16: =IF(H16="","",$N$2) -> CH0706-3 | C16: =IFERROR(IF('Soli_citud '!D14="","",'Soli_citud '!D14),"") -> CINTA FALLA _RIBETE 24 mm CON APRESTO #5 | G16: =IF('Soli_citud '!O14="","",'Soli_citud '!O14) -> m | H16: {=_xlfn.IFS('Soli_citud '!S14="","",'Soli_citud '!S14<=0,"",'Soli_citud '!S14>0,'Soli_citud '!S14)} -> 22.5 | I16: 45456 | J16: 22.5 | K16: {=IFERROR(_xlfn.IFS(H16="","",J16=H16,"Cumplido",J16<H16,H16-J16,J16>H16,"Revisar"),"")} -> Cumplido | N16: 1 | O16: =IFERROR(H16/N16,"") -> 22.5 | P16: {=IFERROR(_xlfn.IFS(Q16>0,"ENTREGADO",'Soli_citud '!A14="HERRAMIENTAS_","DEVOLUTIVO"),"")}
A17: 6 | B17: =IF(H17="","",$N$2) -> CH0706-3 | C17: =IFERROR(IF('Soli_citud '!D15="","",'Soli_citud '!D15),"") -> CORDON TRENZADO ENCERADO VERDE _ CARRETE | G17: =IF('Soli_citud '!O15="","",'Soli_citud '!O15) -> cm | H17: {=_xlfn.IFS('Soli_citud '!S15="","",'Soli_citud '!S15<=0,"",'Soli_citud '!S15>0,'Soli_citud '!S15)} -> 3125 | I17: 45456 | J17: 3125 | K17: {=IFERROR(_xlfn.IFS(H17="","",J17=H17,"Cumplido",J17<H17,H17-J17,J17>H17,"Revisar"),"")} -> Cumplido | N17: 250 | O17: =IFERROR(H17/N17,"") -> 12.5 | P17: {=IFERROR(_xlfn.IFS(Q17>0,"ENTREGADO",'Soli_citud '!A15="HERRAMIENTAS_","DEVOLUTIVO"),"")}
A18: 7 | B18: =IF(H18="","",$N$2) -> CH0706-3 | C18: =IFERROR(IF('Soli_citud '!D16="","",'Soli_citud '!D16),"") -> PEGANTE CEMENTO DE CONTACTO BASE CLOROPRENO | G18: =IF('Soli_citud '!O16="","",'Soli_citud '!O16) -> ml | H18: {=_xlfn.IFS('Soli_citud '!S16="","",'Soli_citud '!S16<=0,"",'Soli_citud '!S16>0,'Soli_citud '!S16)} -> 3600 | I18: 45456 | J18: 3000 | K18: {=IFERROR(_xlfn.IFS(H18="","",J18=H18,"Cumplido",J18<H18,H18-J18,J18>H18,"Revisar"),"")} -> 600 | N18: 3600 | O18: =IFERROR(H18/N18,"") -> 1 | P18: {=IFERROR(_xlfn.IFS(Q18>0,"ENTREGADO",'Soli_citud '!A16="HERRAMIENTAS_","DEVOLUTIVO"),"")}
A19: 8 | B19: =IF(H19="","",$N$2) -> CH0706-3 | C19: =IFERROR(IF('Soli_citud '!D17="","",'Soli_citud '!D17),"") -> SEDA ANTIFLUIDO, VARIOS COLORES | G19: =IF('Soli_citud '!O17="","",'Soli_citud '!O17) -> cm2 | H19: {=_xlfn.IFS('Soli_citud '!S17="","",'Soli_citud '!S17<=0,"",'Soli_citud '!S17>0,'Soli_citud '!S17)} -> 62500 | I19: 45456 | J19: 62500 | K19: {=IFERROR(_xlfn.IFS(H19="","",J19=H19,"Cumplido",J19<H19,H19-J19,J19>H19,"Revisar"),"")} -> Cumplido | N19: 140 | O19: =IFERROR(H19/N19,"") -> 446.42857 | P19: {=IFERROR(_xlfn.IFS(Q19>0,"ENTREGADO",'Soli_citud '!A17="HERRAMIENTAS_","DEVOLUTIVO"),"")}
A20: 9 | B20: =IF(H20="","",$N$2) -> CH0706-3 | C20: =IFERROR(IF('Soli_citud '!D18="","",'Soli_citud '!D18),"") -> YUMBOLON 4mm (CM²) | G20: =IF('Soli_citud '!O18="","",'Soli_citud '!O18) -> cm2 | H20: {=_xlfn.IFS('Soli_citud '!S18="","",'Soli_citud '!S18<=0,"",'Soli_citud '!S18>0,'Soli_citud '!S18)} -> 62500 | I20: 45456 | J20: 62500 | K20: {=IFERROR(_xlfn.IFS(H20="","",J20=H20,"Cumplido",J20<H20,H20-J20,J20>H20,"Revisar"),"")} -> Cumplido | N20: 100 | O20: =IFERROR(H20/N20,"") -> 625 | P20: {=IFERROR(_xlfn.IFS(Q20>0,"ENTREGADO",'Soli_citud '!A18="HERRAMIENTAS_","DEVOLUTIVO"),"")}
A21: 11 | B21: =IF(H21="","",$N$2) -> CH0706-3 | C21: =IFERROR(IF('Soli_citud '!D19="","",'Soli_citud '!D19),"") -> CARTULINA PLANA | G21: =IF('Soli_citud '!O19="","",'Soli_citud '!O19) -> Pliego | H21: {=_xlfn.IFS('Soli_citud '!S19="","",'Soli_citud '!S19<=0,"",'Soli_citud '!S19>0,'Soli_citud '!S19)} -> 32.5 | I21: 45456 | J21: 32 | K21: {=IFERROR(_xlfn.IFS(H21="","",J21=H21,"Cumplido",J21<H21,H21-J21,J21>H21,"Revisar"),"")} -> 0.5 | N21: 1 | O21: =IFERROR(H21/N21,"") -> 32.5 | P21: {=IFERROR(_xlfn.IFS(Q21>0,"ENTREGADO",'Soli_citud '!A19="HERRAMIENTAS_","DEVOLUTIVO"),"")}
A22: 12 | B22: =IF(H22="","",$N$2) | C22: =IFERROR(IF('Soli_citud '!D20="","",'Soli_citud '!D20),"") | G22: =IF('Soli_citud '!O20="","",'Soli_citud '!O20) | H22: {=_xlfn.IFS('Soli_citud '!S20="","",'Soli_citud '!S20<=0,"",'Soli_citud '!S20>0,'Soli_citud '!S20)} | K22: {=IFERROR(_xlfn.IFS(H22="","",J22=H22,"Cumplido",J22<H22,H22-J22,J22>H22,"Revisar"),"")} | O22: =IFERROR(H22/N22,"") | P22: {=IFERROR(_xlfn.IFS(Q22>0,"ENTREGADO",'Soli_citud '!A20="HERRAMIENTAS_","DEVOLUTIVO"),"")}
A23: 13 | B23: =IF(H23="","",$N$2) | C23: =IFERROR(IF('Soli_citud '!D21="","",'Soli_citud '!D21),"") | G23: =IF('Soli_citud '!O21="","",'Soli_citud '!O21) | H23: {=_xlfn.IFS('Soli_citud '!S21="","",'Soli_citud '!S21<=0,"",'Soli_citud '!S21>0,'Soli_citud '!S21)} | K23: {=IFERROR(_xlfn.IFS(H23="","",J23=H23,"Cumplido",J23<H23,H23-J23,J23>H23,"Revisar"),"")} | O23: =IFERROR(H23/N23,"") | P23: {=IFERROR(_xlfn.IFS(Q23>0,"ENTREGADO",'Soli_citud '!A21="HERRAMIENTAS_","DEVOLUTIVO"),"")}
A24: 14 | B24: =IF(H24="","",$N$2) | C24: =IFERROR(IF('Soli_citud '!D22="","",'Soli_citud '!D22),"") | G24: =IF('Soli_citud '!O22="","",'Soli_citud '!O22) | H24: {=_xlfn.IFS('Soli_citud '!S22="","",'Soli_citud '!S22<=0,"",'Soli_citud '!S22>0,'Soli_citud '!S22)} | K24: {=IFERROR(_xlfn.IFS(H24="","",J24=H24,"Cumplido",J24<H24,H24-J24,J24>H24,"Revisar"),"")} | O24: =IFERROR(H24/N24,"") | P24: {=IFERROR(_xlfn.IFS(Q24>0,"ENTREGADO",'Soli_citud '!A22="HERRAMIENTAS_","DEVOLUTIVO"),"")}
A25: 15 | B25: =IF(H25="","",$N$2) | C25: =IFERROR(IF('Soli_citud '!D23="","",'Soli_citud '!D23),"") | G25: =IF('Soli_citud '!O23="","",'Soli_citud '!O23) | H25: {=_xlfn.IFS('Soli_citud '!S23="","",'Soli_citud '!S23<=0,"",'Soli_citud '!S23>0,'Soli_citud '!S23)} | K25: {=IFERROR(_xlfn.IFS(H25="","",J25=H25,"Cumplido",J25<H25,H25-J25,J25>H25,"Revisar"),"")} | O25: =IFERROR(H25/N25,"") | P25: {=IFERROR(_xlfn.IFS(Q25>0,"ENTREGADO",'Soli_citud '!A23="HERRAMIENTAS_","DEVOLUTIVO"),"")}
A26: 16 | B26: =IF(H26="","",$N$2) | C26: =IFERROR(IF('Soli_citud '!D24="","",'Soli_citud '!D24),"") | G26: =IF('Soli_citud '!O24="","",'Soli_citud '!O24) | H26: {=_xlfn.IFS('Soli_citud '!S24="","",'Soli_citud '!S24<=0,"",'Soli_citud '!S24>0,'Soli_citud '!S24)} | K26: {=IFERROR(_xlfn.IFS(H26="","",J26=H26,"Cumplido",J26<H26,H26-J26,J26>H26,"Revisar"),"")} | O26: =IFERROR(H26/N26,"") | P26: {=IFERROR(_xlfn.IFS(Q26>0,"ENTREGADO",'Soli_citud '!A24="HERRAMIENTAS_","DEVOLUTIVO"),"")}
A27: 17 | B27: =IF(H27="","",$N$2) | C27: =IFERROR(IF('Soli_citud '!D25="","",'Soli_citud '!D25),"") | G27: =IF('Soli_citud '!O25="","",'Soli_citud '!O25) | H27: {=_xlfn.IFS('Soli_citud '!S25="","",'Soli_citud '!S25<=0,"",'Soli_citud '!S25>0,'Soli_citud '!S25)} | K27: {=IFERROR(_xlfn.IFS(H27="","",J27=H27,"Cumplido",J27<H27,H27-J27,J27>H27,"Revisar"),"")} | O27: =IFERROR(H27/N27,"") | P27: {=IFERROR(_xlfn.IFS(Q27>0,"ENTREGADO",'Soli_citud '!A25="HERRAMIENTAS_","DEVOLUTIVO"),"")}
A28: 18 | B28: =IF(H28="","",$N$2) | C28: =IFERROR(IF('Soli_citud '!D26="","",'Soli_citud '!D26),"") | G28: =IF('Soli_citud '!O26="","",'Soli_citud '!O26) | H28: {=_xlfn.IFS('Soli_citud '!S26="","",'Soli_citud '!S26<=0,"",'Soli_citud '!S26>0,'Soli_citud '!S26)} | K28: {=IFERROR(_xlfn.IFS(H28="","",J28=H28,"Cumplido",J28<H28,H28-J28,J28>H28,"Revisar"),"")} | O28: =IFERROR(H28/N28,"") | P28: {=IFERROR(_xlfn.IFS(Q28>0,"ENTREGADO",'Soli_citud '!A26="HERRAMIENTAS_","DEVOLUTIVO"),"")}
A29: 19 | B29: =IF(H29="","",$N$2) | C29: =IFERROR(IF('Soli_citud '!D27="","",'Soli_citud '!D27),"") | G29: =IF('Soli_citud '!O27="","",'Soli_citud '!O27) | H29: {=_xlfn.IFS('Soli_citud '!S27="","",'Soli_citud '!S27<=0,"",'Soli_citud '!S27>0,'Soli_citud '!S27)} | K29: {=IFERROR(_xlfn.IFS(H29="","",J29=H29,"Cumplido",J29<H29,H29-J29,J29>H29,"Revisar"),"")} | O29: =IFERROR(H29/N29,"") | P29: {=IFERROR(_xlfn.IFS(Q29>0,"ENTREGADO",'Soli_citud '!A27="HERRAMIENTAS_","DEVOLUTIVO"),"")}
A30: 20 | B30: =IF(H30="","",$N$2) | C30: =IFERROR(IF('Soli_citud '!D28="","",'Soli_citud '!D28),"") | G30: =IF('Soli_citud '!O28="","",'Soli_citud '!O28) | H30: {=_xlfn.IFS('Soli_citud '!S28="","",'Soli_citud '!S28<=0,"",'Soli_citud '!S28>0,'Soli_citud '!S28)} | K30: {=IFERROR(_xlfn.IFS(H30="","",J30=H30,"Cumplido",J30<H30,H30-J30,J30>H30,"Revisar"),"")} | O30: =IFERROR(H30/N30,"") | P30: {=IFERROR(_xlfn.IFS(Q30>0,"ENTREGADO",'Soli_citud '!A28="HERRAMIENTAS_","DEVOLUTIVO"),"")}
A31: 21 | B31: =IF(H31="","",$N$2) | C31: =IFERROR(IF('Soli_citud '!D29="","",'Soli_citud '!D29),"") | G31: =IF('Soli_citud '!O29="","",'Soli_citud '!O29) | H31: {=_xlfn.IFS('Soli_citud '!S29="","",'Soli_citud '!S29<=0,"",'Soli_citud '!S29>0,'Soli_citud '!S29)} | K31: {=IFERROR(_xlfn.IFS(H31="","",J31=H31,"Cumplido",J31<H31,H31-J31,J31>H31,"Revisar"),"")} | O31: =IFERROR(H31/N31,"") | P31: {=IFERROR(_xlfn.IFS(Q31>0,"ENTREGADO",'Soli_citud '!A29="HERRAMIENTAS_","DEVOLUTIVO"),"")}
A32: 22 | B32: =IF(H32="","",$N$2) | C32: =IFERROR(IF('Soli_citud '!D30="","",'Soli_citud '!D30),"") | G32: =IF('Soli_citud '!O30="","",'Soli_citud '!O30) | H32: {=_xlfn.IFS('Soli_citud '!S30="","",'Soli_citud '!S30<=0,"",'Soli_citud '!S30>0,'Soli_citud '!S30)} | K32: {=IFERROR(_xlfn.IFS(H32="","",J32=H32,"Cumplido",J32<H32,H32-J32,J32>H32,"Revisar"),"")} | O32: =IFERROR(H32/N32,"") | P32: {=IFERROR(_xlfn.IFS(Q32>0,"ENTREGADO",'Soli_citud '!A30="HERRAMIENTAS_","DEVOLUTIVO"),"")}

Sheet BD
E1: Total de items en el ALMACÉN. Excepto: Papelería, Formación y Químicos | H1: Insumos anexados 2024, en este color | Z1: Bede
E3: =SUM(Total_AdhySol,Total_SECUNDARIO_MEDULAR,Total_Cuero,Total_Herrajes,Total_Sint_y_Tex,Total_Suelas,Total_Herramientas,Total_Ins_Compl) -> 860
A6: Totales | B6: =SUBTOTAL(3,(BD!$B$8:$B$20)) -> 13 | H6: Magnitudes para calculo minimo
A7: Item | B7: Material | C7: Categoría | D7: Unidad de Compra Almacen | E7: Precio Unidad de Compra ( $) | F7: Unidad Despacho Almacen | G7: Valor /U Despacho en Almacen | H7: Magnitud 1 en U | I7: Magnitud 2 en U | J7: Codigo en el Almacén | K7: Descripción
A8: 1 | B8: ADHESIVO PU | C8: ADHESIVOS_Solventes | D8: gal | E8: 74650 | F8: ml | G8: =IF(BD!$E8="","",(E8/(H8*I8))) -> 19.722589 | H8: 3785 | I8: 1 | J8: =CONCATENATE(LEFT(C8,1),MID(C8,SEARCH("_",C8)+1,2),TEXT(A8,"000")) -> ASo001
A9: =A8+1 -> 2 | B9: AQUAPREN CALZADO Y MARROQUINERÍA SPRAY | C9: ADHESIVOS_Solventes | D9: gal | E9: 231671.5 | F9: ml | G9: =IF(BD!$E9="","",(E9/(H9*I9))) -> 61.207794 | H9: 3785 | I9: 1 | J9: =CONCATENATE(LEFT(C9,1),MID(C9,SEARCH("_",C9)+1,2),TEXT(A9,"000")) -> ASo002
A10: =A9+1 -> 3 | B10: AQUAPREN GUARNECIDA | C10: ADHESIVOS_Solventes | D10: gal | E10: 231671.5 | F10: ml | G10: =IF(BD!$E10="","",(E10/(H10*I10))) -> 61.207794 | H10: 3785 | I10: 1 | J10: =CONCATENATE(LEFT(C10,1),MID(C10,SEARCH("_",C10)+1,2),TEXT(A10,"000")) -> ASo003
A11: =A10+1 -> 4 | B11: CARDA RAPIDO | C11: ADHESIVOS_Solventes | D11: gal | E11: 78666.625 | F11: ml | G11: =IF(BD!$E11="","",(E11/(H11*I11))) -> 20.783785 | H11: 3785 | I11: 1 | J11: =CONCATENATE(LEFT(C11,1),MID(C11,SEARCH("_",C11)+1,2),TEXT(A11,"000")) -> ASo004
A12: =A11+1 -> 5 | B12: DILUSOR DE PINTURA 2-THIN | C12: ADHESIVOS_Solventes | D12: U | E12: 72665 | F12: U | G12: =IF(BD!$E12="","",(E12/(H12*I12))) -> 72665 | H12: 1 | I12: 1 | J12: =CONCATENATE(LEFT(C12,1),MID(C12,SEARCH("_",C12)+1,2),TEXT(A12,"000")) -> ASo005
A13: =A12+1 -> 6 | B13: HALOGENANTE | C13: ADHESIVOS_Solventes | D13: gal | E13: 59690.625 | F13: ml | G13: =IF(BD!$E13="","",(E13/(H13*I13))) -> 15.77031 | H13: 3785 | I13: 1 | J13: =CONCATENATE(LEFT(C13,1),MID(C13,SEARCH("_",C13)+1,2),TEXT(A13,"000")) -> ASo006
A14: =A13+1 -> 7 | B14: LIMPIADOR DE SUELAS | C14: ADHESIVOS_Solventes | D14: gal | E14: 50200 | F14: ml | G14: =IF(BD!$E14="","",(E14/(H14*I14))) -> 13.26288 | H14: 3785 | I14: 1 | J14: =CONCATENATE(LEFT(C14,1),MID(C14,SEARCH("_",C14)+1,2),TEXT(A14,"000")) -> ASo007
A15: =A14+1 -> 8 | B15: PEGANTE CEMENTO DE CONTACTO BASE CLOROPRENO | C15: ADHESIVOS_Solventes | D15: gal | E15: 66108 | F15: ml | G15: =IF(BD!$E15="","",(E15/(H15*I15))) -> 17.465786 | H15: 3785 | I15: 1 | J15: =CONCATENATE(LEFT(C15,1),MID(C15,SEARCH("_",C15)+1,2),TEXT(A15,"000")) -> ASo008
A16: =A15+1 -> 9 | B16: PRIMER EVA | C16: ADHESIVOS_Solventes | D16: gal | F16: ml | G16: =IF(BD!$E16="","",(E16/(H16*I16))) | H16: 3785 | I16: 1 | J16: =CONCATENATE(LEFT(C16,1),MID(C16,SEARCH("_",C16)+1,2),TEXT(A16,"000")) -> ASo009
A17: =A16+1 -> 10 | B17: PRIMER PU | C17: ADHESIVOS_Solventes | D17: gal | E17: 61960 | F17: ml | G17: =IF(BD!$E17="","",(E17/(H17*I17))) -> 16.369881 | H17: 3785 | I17: 1 | J17: =CONCATENATE(LEFT(C17,1),MID(C17,SEARCH("_",C17)+1,2),TEXT(A17,"000")) -> ASo010
A18: =A17+1 -> 11 | B18: SOLUCIÓN DE CAUCHO | C18: ADHESIVOS_Solventes | D18: gal | E18: 28400 | F18: ml | G18: =IF(BD!$E18="","",(E18/(H18*I18))) -> 7.5033025 | H18: 3785 | I18: 1 | J18: =CONCATENATE(LEFT(C18,1),MID(C18,SEARCH("_",C18)+1,2),TEXT(A18,"000")) -> ASo011
A19: =A18+1 -> 12 | B19: THINNER | C19: ADHESIVOS_Solventes | D19: gal | E19: 36816 | F19: gal | G19: =IF(BD!$E19="","",(E19/(H19*I19))) -> 36816 | H19: 1 | I19: 1 | J19: =CONCATENATE(LEFT(C19,1),MID(C19,SEARCH("_",C19)+1,2),TEXT(A19,"000")) -> ASo012
A20: =A19+1 -> 13 | B20: VULCANIZANTE | C20: ADHESIVOS_Solventes | D20: ml | F20: ml | H20: 1 | I20: 1 | J20: ASo013
B57: Insertar Filas!!
A60: Totales | B60: =SUBTOTAL(3,(B62:B169)) -> 108
A61: Item | B61: Material | C61: Categoría | D61: Unidad de Compra Almacen | E61: Precio Unidad de Compra ( $) | F61: Unidad Despacho Almacen | G61: Valor /U Despacho en Almacen | H61: Magnitud 1 en U | I61: Magnitud 2 en U | J61: Codigo en el Almacén | K61: Descripción
A62: 1 | B62: AGUJAS PARA INFLAR BALONES | C62: FORMACION | D62: U | E62: 8995 | F62: U | G62: =IF(BD!$E62="","",(E62/(H62*I62))) -> 8995 | H62: 1 | I62: 1 | J62: =CONCATENATE(LEFT(C62,1),"_",TEXT(A62,"000")) -> F_001
A63: =A62+1 -> 2 | B63: ARO DE PISO PLANO | C63: FORMACION | D63: U | E63: 109707 | F63: U | G63: =IF(BD!$E63="","",(E63/(H63*I63))) -> 109707 | H63: 1 | I63: 1 | J63: =CONCATENATE(LEFT(C63,1),"_",TEXT(A63,"000")) -> F_002
A64: =A63+1 -> 3 | B64: ARO ULA REDONDO | C64: FORMACION | D64: U | E64: 65500 | F64: U | G64: =IF(BD!$E64="","",(E64/(H64*I64))) -> 65500 | H64: 1 | I64: 1 | J64: =CONCATENATE(LEFT(C64,1),"_",TEXT(A64,"000")) -> F_003
A65: =A64+1 -> 4 | B65: AVISO_CAL (VARIOS DE MERCANCIAS PELIGROSAS, DE 1 CLASE) | C65: FORMACION | D65: U | E65: 24994 | F65: U | G65: =IF(BD!$E65="","",(E65/(H65*I65))) -> 24994 | H65: 1 | I65: 1 | J65: =CONCATENATE(LEFT(C65,1),"_",TEXT(A65,"000")) -> F_004
A66: =A65+1 -> 5 | B66: AVISO_CAL ,SGA, MEDIDAS 25X25, (ETIQUETADO PARA TRANSPORTES) CLASE 1 SUSTANCIAS Y OBJETO EXPLOSIVOS: 1.1 | C66: FORMACION | D66: U | E66: 20237 | F66: U | G66: =IF(BD!$E66="","",(E66/(H66*I66))) -> 20237 | H66: 1 | I66: 1 | J66: =CONCATENATE(LEFT(C66,1),"_",TEXT(A66,"000")) -> F_005
A67: =A66+1 -> 6 | B67: AVISO_CAL ,SGA, MEDIDAS 25X25, (ETIQUETADO PARA TRANSPORTES) CLASE 1 SUSTANCIAS Y OBJETO EXPLOSIVOS: 1.2 | C67: FORMACION | D67: U | E67: 24994 | F67: U | G67: =IF(BD!$E67="","",(E67/(H67*I67))) -> 24994 | H67: 1 | I67: 1 | J67: =CONCATENATE(LEFT(C67,1),"_",TEXT(A67,"000")) -> F_006
A68: =A67+1 -> 7 | B68: AVISO_CAL ,SGA, MEDIDAS 25X25, (ETIQUETADO PARA TRANSPORTES) CLASE 1 SUSTANCIAS Y OBJETO EXPLOSIVOS: 1.3 | C68: FORMACION | D68: U | E68: 24994 | F68: U | G68: =IF(BD!$E68="","",(E68/(H68*I68))) -> 24994 | H68: 1 | I68: 1 | J68: =CONCATENATE(LEFT(C68,1),"_",TEXT(A68,"000")) -> F_007
A69: =A68+1 -> 8 | B69: AVISO_CAL ,SGA, MEDIDAS 25X25, (ETIQUETADO PARA TRANSPORTES) CLASE 1 SUSTANCIAS Y OBJETO EXPLOSIVOS: 1.4 | C69: FORMACION | D69: U | E69: 24994 | F69: U | G69: =IF(BD!$E69="","",(E69/(H69*I69))) -> 24994 | H69: 1 | I69: 1 | J69: =CONCATENATE(LEFT(C69,1),"_",TEXT(A69,"000")) -> F_008
A70: =A69+1 -> 9 | B70: AVISO_CAL ,SGA, MEDIDAS 25X25, (ETIQUETADO PARA TRANSPORTES) CLASE 1 SUSTANCIAS Y OBJETO EXPLOSIVOS: 1.5 | C70: FORMACION | D70: U | E70: 24994 | F70: U | G70: =IF(BD!$E70="","",(E70/(H70*I70))) -> 24994 | H70: 1 | I70: 1 | J70: =CONCATENATE(LEFT(C70,1),"_",TEXT(A70,"000")) -> F_009
A71: =A70+1 -> 10 | B71: AVISO_CAL ,SGA, MEDIDAS 25X25, (ETIQUETADO PARA TRANSPORTES) CLASE 1 SUSTANCIAS Y OBJETO EXPLOSIVOS: 1.6 | C71: FORMACION | D71: U | E71: 24994 | F71: U | G71: =IF(BD!$E71="","",(E71/(H71*I71))) -> 24994 | H71: 1 | I71: 1 | J71: =CONCATENATE(LEFT(C71,1),"_",TEXT(A71,"000")) -> F_010
A72: =A71+1 -> 11 | B72: AVISO_CAL ,SGA, MEDIDAS 25X25, (ETIQUETADO PARA TRANSPORTES) CLASE 2 GASES: GAS INFLAMABLE | C72: FORMACION | D72: U | E72: 24994 | F72: U | G72: =IF(BD!$E72="","",(E72/(H72*I72))) -> 24994 | H72: 1 | I72: 1 | J72: =CONCATENATE(LEFT(C72,1),"_",TEXT(A72,"000")) -> F_011
A73: =A72+1 -> 12 | B73: AVISO_CAL ,SGA, MEDIDAS 25X25, (ETIQUETADO PARA TRANSPORTES) CLASE 2 GASES: GAS NO INFLAMABLE | C73: FORMACION | D73: U | E73: 24994 | F73: U | G73: =IF(BD!$E73="","",(E73/(H73*I73))) -> 24994 | H73: 1 | I73: 1 | J73: =CONCATENATE(LEFT(C73,1),"_",TEXT(A73,"000")) -> F_012
A74: =A73+1 -> 13 | B74: AVISO_CAL ,SGA, MEDIDAS 25X25, (ETIQUETADO PARA TRANSPORTES) CLASE 2 GASES: GAS TOXICO | C74: FORMACION | D74: U | E74: 24994 | F74: U | G74: =IF(BD!$E74="","",(E74/(H74*I74))) -> 24994 | H74: 1 | I74: 1 | J74: =CONCATENATE(LEFT(C74,1),"_",TEXT(A74,"000")) -> F_013
... A169: =A168+1 -> 108 | B169: VISOR POLICARBONATO, PARA CARETA DE ESMERILAR | C169: FORMACION | D169: U | E169: 16548 | F169: U | G169: =IF(BD!$E169="","",(E169/(H169*I169))) -> 16548 | H169: 1 | I169: 1 | J169: =CONCATENATE(LEFT(C169,1),"_",TEXT(A169,"000")) -> F_108
B212: Insertar Filas!!
A215: Totales | B215: =SUBTOTAL(3,(B217:B430)) -> 214
A216: Item | B216: Material | C216: Categoría | D216: Unidad de Compra Almacen | E216: Precio Unidad de Compra ( $) | F216: Unidad Despacho Almacen | G216: Valor /U Despacho en Almacen | H216: Magnitud 1 en U | I216: Magnitud 2 en U | J216: Codigo en el Almacén | K216: Descripción
A217: 1 | B217: CAMBRIÓN | C217: SECUNDARIO_MEDULAR | D217: Par | E217: 760 | F217: Par | G217: =IF(BD!$E217="","",(E217/(H217*I217))) -> 760 | H217: 1 | I217: 1 | J217: =CONCATENATE(LEFT(C217,1),MID(C217,SEARCH("_",C217)+1,2),TEXT(A217,"000")) -> SME001
A218: 128 | B218: CARTON PIEDRA BARTOLLI _ | C218: SECUNDARIO_MEDULAR | D218: m | F218: cm | G218: =IF(BD!$E218="","",(E218/(H218*I218))) | H218: 1 | I218: 100 | J218: =CONCATENATE(LEFT(C218,1),MID(C218,SEARCH("_",C218)+1,2),TEXT(A218,"000")) -> SME128
A219: 2 | B219: CAUCHO LATEX | C219: SECUNDARIO_MEDULAR | D219: Lámina | E219: 45667 | F219: Lámina | G219: =IF(BD!$E219="","",(E219/(H219*I219))) -> 45667 | H219: 1 | I219: 1 | J219: =CONCATENATE(LEFT(C219,1),MID(C219,SEARCH("_",C219)+1,2),TEXT(A219,"000")) -> SME002
A220: 128 | B220: CINTA FALLA 20 mm azul oscuro _ rollo | C220: SECUNDARIO_MEDULAR | D220: m | F220: cm | G220: =IF(BD!$E220="","",(E220/(H220*I220))) | H220: 1 | I220: 100 | J220: =CONCATENATE(LEFT(C220,1),MID(C220,SEARCH("_",C220)+1,2),TEXT(A220,"000")) -> SME128
A221: 128 | B221: CINTA FALLA 20 mm azul turquesa _ rollo | C221: SECUNDARIO_MEDULAR | D221: m | F221: cm | G221: =IF(BD!$E221="","",(E221/(H221*I221))) | H221: 1 | I221: 100 | J221: =CONCATENATE(LEFT(C221,1),MID(C221,SEARCH("_",C221)+1,2),TEXT(A221,"000")) -> SME128
A222: 128 | B222: CINTA FALLA 20 mm blanco mugre _ rollo | C222: SECUNDARIO_MEDULAR | D222: m | F222: cm | G222: =IF(BD!$E222="","",(E222/(H222*I222))) | H222: 1 | I222: 100 | J222: =CONCATENATE(LEFT(C222,1),MID(C222,SEARCH("_",C222)+1,2),TEXT(A222,"000")) -> SME128
A223: 128 | B223: CINTA FALLA 20 mm café _ rollo | C223: SECUNDARIO_MEDULAR | D223: m | F223: cm | G223: =IF(BD!$E223="","",(E223/(H223*I223))) | H223: 1 | I223: 100 | J223: =CONCATENATE(LEFT(C223,1),MID(C223,SEARCH("_",C223)+1,2),TEXT(A223,"000")) -> SME128
A224: 128 | B224: CINTA FALLA 20 mm gris _ rollo | C224: SECUNDARIO_MEDULAR | D224: m | F224: cm | G224: =IF(BD!$E224="","",(E224/(H224*I224))) | H224: 1 | I224: 100 | J224: =CONCATENATE(LEFT(C224,1),MID(C224,SEARCH("_",C224)+1,2),TEXT(A224,"000")) -> SME128
A225: 128 | B225: CINTA FALLA 20 mm rojo _ rollo | C225: SECUNDARIO_MEDULAR | D225: m | F225: cm | G225: =IF(BD!$E225="","",(E225/(H225*I225))) | H225: 1 | I225: 100 | J225: =CONCATENATE(LEFT(C225,1),MID(C225,SEARCH("_",C225)+1,2),TEXT(A225,"000")) -> SME128
A226: 128 | B226: CINTA FALLA 25 mm beige _ rollo | C226: SECUNDARIO_MEDULAR | D226: m | F226: cm | G226: =IF(BD!$E226="","",(E226/(H226*I226))) | H226: 1 | I226: 100 | J226: =CONCATENATE(LEFT(C226,1),MID(C226,SEARCH("_",C226)+1,2),TEXT(A226,"000")) -> SME128
A227: 128 | B227: CINTA FALLA 25 mm blanco _ rollo | C227: SECUNDARIO_MEDULAR | D227: m | F227: cm | G227: =IF(BD!$E227="","",(E227/(H227*I227))) | H227: 1 | I227: 100 | J227: =CONCATENATE(LEFT(C227,1),MID(C227,SEARCH("_",C227)+1,2),TEXT(A227,"000")) -> SME128
A228: 128 | B228: CINTA FALLA 25 mm rojo _ rollo | C228: SECUNDARIO_MEDULAR | D228: m | F228: cm | G228: =IF(BD!$E228="","",(E228/(H228*I228))) | H228: 1 | I228: 100 | J228: =CONCATENATE(LEFT(C228,1),MID(C228,SEARCH("_",C228)+1,2),TEXT(A228,"000")) -> SME128
A229: 3 | B229: CINTA FALLA _RIBETE 18 mm CON APRESTO #3 | C229: SECUNDARIO_MEDULAR | D229: Rollo | E229: 41000 | F229: m | G229: =IF(BD!$E229="","",(E229/(H229*I229))) -> 410 | H229: 100 | I229: 1 | J229: =CONCATENATE(LEFT(C229,1),MID(C229,SEARCH("_",C229)+1,2),TEXT(A229,"000")) -> SME003
A230: 4 | B230: CINTA FALLA _RIBETE 24 mm CON APRESTO #5 | C230: SECUNDARIO_MEDULAR | D230: Rollo | E230: 58500 | F230: m | G230: =IF(BD!$E230="","",(E230/(H230*I230))) -> 585 | H230: 100 | I230: 1 | J230: =CONCATENATE(LEFT(C230,1),MID(C230,SEARCH("_",C230)+1,2),TEXT(A230,"000")) -> SME004
A231: 5 | B231: COMFORTEX CALIBRE 1.5mm. | C231: SECUNDARIO_MEDULAR | D231: Lámina | E231: 17830 | F231: cm2 | G231: =IF(BD!$E231="","",(E231/(H231*I231))) -> 1.2735714 | H231: 140 | I231: 100 | J231: =CONCATENATE(LEFT(C231,1),MID(C231,SEARCH("_",C231)+1,2),TEXT(A231,"000")) -> SME005
A232: 42 | B232: Cordon ENCERADO NEGRO 110cm | C232: SECUNDARIO_MEDULAR | D232: Par | E232: 639 | F232: Par | G232: =IF(BD!$E232="","",(E232/(H232*I232))) -> 639 | H232: 1 | I232: 1 | J232: =CONCATENATE(LEFT(C232,1),MID(C232,SEARCH("_",C232)+1,2),TEXT(A232,"000")) -> SME042
A233: 43 | B233: CORDON ENCERADO NEGRO LARGO | C233: SECUNDARIO_MEDULAR | D233: Par | E233: 639 | F233: Par | G233: =IF(BD!$E233="","",(E233/(H233*I233))) -> 639 | H233: 1 | I233: 1 | J233: =CONCATENATE(LEFT(C233,1),MID(C233,SEARCH("_",C233)+1,2),TEXT(A233,"000")) -> SME043
A234: 44 | B234: CORDON ENCERADO PLANO CAFE | C234: SECUNDARIO_MEDULAR | D234: Par | E234: 639 | F234: Par | G234: =IF(BD!$E234="","",(E234/(H234*I234))) -> 639 | H234: 1 | I234: 1 | J234: =CONCATENATE(LEFT(C234,1),MID(C234,SEARCH("_",C234)+1,2),TEXT(A234,"000")) -> SME044
A235: 45 | B235: CORDON ENCERADO PLANO NEGRO | C235: SECUNDARIO_MEDULAR | D235: Par | E235: 639 | F235: Par | G235: =IF(BD!$E235="","",(E235/(H235*I235))) -> 639 | H235: 1 | I235: 1 | J235: =CONCATENATE(LEFT(C235,1),MID(C235,SEARCH("_",C235)+1,2),TEXT(A235,"000")) -> SME045
A236: 46 | B236: CORDON ENCERADO REDODNDO CAFE | C236: SECUNDARIO_MEDULAR | D236: Par | E236: 639 | F236: Par | G236: =IF(BD!$E236="","",(E236/(H236*I236))) -> 639 | H236: 1 | I236: 1 | J236: =CONCATENATE(LEFT(C236,1),MID(C236,SEARCH("_",C236)+1,2),TEXT(A236,"000")) -> SME046
A237: 47 | B237: CORDON NEGRO PLANO | C237: SECUNDARIO_MEDULAR | D237: Par | E237: 639 | F237: Par | G237: =IF(BD!$E237="","",(E237/(H237*I237))) -> 639 | H237: 1 | I237: 1 | J237: =CONCATENATE(LEFT(C237,1),MID(C237,SEARCH("_",C237)+1,2),TEXT(A237,"000")) -> SME047
A238: 48 | B238: CORDON NEGRO REDONDO | C238: SECUNDARIO_MEDULAR | D238: Par | E238: 639 | F238: Par | G238: =IF(BD!$E238="","",(E238/(H238*I238))) -> 639 | H238: 1 | I238: 1 | J238: =CONCATENATE(LEFT(C238,1),MID(C238,SEARCH("_",C238)+1,2),TEXT(A238,"000")) -> SME048
A239: 49 | B239: CORDON PLANO | C239: SECUNDARIO_MEDULAR | D239: Par | E239: 639 | F239: Par | G239: =IF(BD!$E239="","",(E239/(H239*I239))) -> 639 | H239: 1 | I239: 1 | J239: =CONCATENATE(LEFT(C239,1),MID(C239,SEARCH("_",C239)+1,2),TEXT(A239,"000")) -> SME049
A240: 6 | B240: Cordon PLANO AZUL OSCURO 110cm | C240: SECUNDARIO_MEDULAR | D240: Par | E240: 639 | F240: Par | G240: =IF(BD!$E240="","",(E240/(H240*I240))) -> 639 | H240: 1 | I240: 1 | J240: =CONCATENATE(LEFT(C240,1),MID(C240,SEARCH("_",C240)+1,2),TEXT(A240,"000")) -> SME006
... A288: 65 | B288: CORDON REDONDO ROJO | C288: SECUNDARIO_MEDULAR | D288: Par | E288: 475.34 | F288: Par | G288: =IF(BD!$E288="","",(E288/(H288*I288))) -> 475.34 | H288: 1 | I288: 1 | J288: =CONCATENATE(LEFT(C288,1),MID(C288,SEARCH("_",C288)+1,2),TEXT(A288,"000")) -> SME065
A289: 128 | B289: CORDON TRENZADO ENCERADO AMARILLO _ CARRETE | C289: SECUNDARIO_MEDULAR | D289: m | F289: cm | G289: =IF(BD!$E289="","",(E289/(H289*I289))) | H289: 1 | I289: 100 | J289: =CONCATENATE(LEFT(C289,1),MID(C289,SEARCH("_",C289)+1,2),TEXT(A289,"000")) -> SME128
A290: 128 | B290: CORDON TRENZADO ENCERADO BLANCO _ CARRETE | C290: SECUNDARIO_MEDULAR | D290: m | F290: cm | G290: =IF(BD!$E290="","",(E290/(H290*I290))) | H290: 1 | I290: 100 | J290: =CONCATENATE(LEFT(C290,1),MID(C290,SEARCH("_",C290)+1,2),TEXT(A290,"000")) -> SME128
A291: 128 | B291: CORDON TRENZADO ENCERADO FUCSIA _ CARRETE | C291: SECUNDARIO_MEDULAR | D291: m | F291: cm | G291: =IF(BD!$E291="","",(E291/(H291*I291))) | H291: 1 | I291: 100 | J291: =CONCATENATE(LEFT(C291,1),MID(C291,SEARCH("_",C291)+1,2),TEXT(A291,"000")) -> SME128
A292: 128 | B292: CORDON TRENZADO ENCERADO LILA _ CARRETE | C292: SECUNDARIO_MEDULAR | D292: m | F292: cm | G292: =IF(BD!$E292="","",(E292/(H292*I292))) | H292: 1 | I292: 100 | J292: =CONCATENATE(LEFT(C292,1),MID(C292,SEARCH("_",C292)+1,2),TEXT(A292,"000")) -> SME128
A293: 128 | B293: CORDON TRENZADO ENCERADO VERDE _ CARRETE | C293: SECUNDARIO_MEDULAR | D293: m | F293: cm | G293: =IF(BD!$E293="","",(E293/(H293*I293))) | H293: 1 | I293: 100 | J293: =CONCATENATE(LEFT(C293,1),MID(C293,SEARCH("_",C293)+1,2),TEXT(A293,"000")) -> SME128
A294: 66 | B294: CORDON TRENZADO ENCERADO | C294: SECUNDARIO_MEDULAR | D294: Par | E294: 475.34 | F294: Par | G294: =IF(BD!$E294="","",(E294/(H294*I294))) -> 475.34 | H294: 1 | I294: 1 | J294: =CONCATENATE(LEFT(C294,1),MID(C294,SEARCH("_",C294)+1,2),TEXT(A294,"000")) -> SME066
A295: 67 | B295: CREMALLERA EVERBRIGTH #5 | C295: SECUNDARIO_MEDULAR | D295: m | E295: 9800 | F295: cm | G295: =IF(BD!$E295="","",(E295/(H295*I295))) -> 98 | H295: 100 | I295: 1 | J295: =CONCATENATE(LEFT(C295,1),MID(C295,SEARCH("_",C295)+1,2),TEXT(A295,"000")) -> SME067
A296: 68 | B296: CREMALLERA POLIÉSTER #3 | C296: SECUNDARIO_MEDULAR | D296: m | E296: 943.5 | F296: cm | G296: =IF(BD!$E296="","",(E296/(H296*I296))) -> 9.435 | H296: 100 | I296: 1 | J296: =CONCATENATE(LEFT(C296,1),MID(C296,SEARCH("_",C296)+1,2),TEXT(A296,"000")) -> SME068
A297: 69 | B297: CREMALLERA POLIÉSTER #4 | C297: SECUNDARIO_MEDULAR | D297: m | E297: 943.5 | F297: cm | G297: =IF(BD!$E297="","",(E297/(H297*I297))) -> 9.435 | H297: 100 | I297: 1 | J297: =CONCATENATE(LEFT(C297,1),MID(C297,SEARCH("_",C297)+1,2),TEXT(A297,"000")) -> SME069
A298: 70 | B298: CREMALLERA POLIÉSTER #6 | C298: SECUNDARIO_MEDULAR | D298: m | E298: 1223 | F298: cm | G298: =IF(BD!$E298="","",(E298/(H298*I298))) -> 12.23 | H298: 100 | I298: 1 | J298: =CONCATENATE(LEFT(C298,1),MID(C298,SEARCH("_",C298)+1,2),TEXT(A298,"000")) -> SME070
A299: 71 | B299: D40 EXTRAFOAM 1 | C299: SECUNDARIO_MEDULAR | D299: Lámina | E299: 16471.25 | F299: Lámina | G299: =IF(BD!$E299="","",(E299/(H299*I299))) -> 16471.25 | H299: 1 | I299: 1 | J299: =CONCATENATE(LEFT(C299,1),MID(C299,SEARCH("_",C299)+1,2),TEXT(A299,"000")) -> SME071
A300: 72 | B300: D40 EXTRAFOAM 2 | C300: SECUNDARIO_MEDULAR | D300: Lámina | E300: 32931.5 | F300: Lámina | G300: =IF(BD!$E300="","",(E300/(H300*I300))) -> 32931.5 | H300: 1 | I300: 1 | J300: =CONCATENATE(LEFT(C300,1),MID(C300,SEARCH("_",C300)+1,2),TEXT(A300,"000")) -> SME072
A301: 73 | B301: D40 EXTRAFOAM 3 | C301: SECUNDARIO_MEDULAR | D301: Lámina | E301: 16209.5 | F301: Lámina | G301: =IF(BD!$E301="","",(E301/(H301*I301))) -> 16209.5 | H301: 1 | I301: 1 | J301: =CONCATENATE(LEFT(C301,1),MID(C301,SEARCH("_",C301)+1,2),TEXT(A301,"000")) -> SME073
A302: 74 | B302: D40 EXTRAFOAM 4 | C302: SECUNDARIO_MEDULAR | D302: Lámina | E302: 32417 | F302: Lámina | G302: =IF(BD!$E302="","",(E302/(H302*I302))) -> 32417 | H302: 1 | I302: 1 | J302: =CONCATENATE(LEFT(C302,1),MID(C302,SEARCH("_",C302)+1,2),TEXT(A302,"000")) -> SME074
A303: 75 | B303: D60 HD FOAM | C303: SECUNDARIO_MEDULAR | D303: Lámina | E303: 50250 | F303: Lámina | G303: =IF(BD!$E303="","",(E303/(H303*I303))) -> 50250 | H303: 1 | I303: 1 | J303: =CONCATENATE(LEFT(C303,1),MID(C303,SEARCH("_",C303)+1,2),TEXT(A303,"000")) -> SME075
A304: 76 | B304: D60 HD FOAM | C304: SECUNDARIO_MEDULAR | D304: Lámina | E304: 25131.5 | F304: Lámina | G304: =IF(BD!$E304="","",(E304/(H304*I304))) -> 25131.5 | H304: 1 | I304: 1 | J304: =CONCATENATE(LEFT(C304,1),MID(C304,SEARCH("_",C304)+1,2),TEXT(A304,"000")) -> SME076
A305: 77 | B305: ELASTICO | C305: SECUNDARIO_MEDULAR | D305: Rollo | E305: 3700 | F305: cm2 | G305: =IF(BD!$E305="","",(E305/(H305*I305))) -> 26.428571 | H305: 140 | I305: 1 | J305: =CONCATENATE(LEFT(C305,1),MID(C305,SEARCH("_",C305)+1,2),TEXT(A305,"000")) -> SME077
... A312: 84 | B312: ESPUMA MULTIFORM DENSIDAD 40 DE 5 mm | C312: SECUNDARIO_MEDULAR | D312: m | E312: 20000 | F312: cm2 | G312: =IF(BD!$E312="","",(E312/(H312*I312))) -> 1 | H312: 200 | I312: 100 | J312: =CONCATENATE(LEFT(C312,1),MID(C312,SEARCH("_",C312)+1,2),TEXT(A312,"000")) -> SME084
A313: 128 | B313: ESPUMA PARA ABULLONADO HOJAS GRIS _ | C313: SECUNDARIO_MEDULAR | D313: m | F313: cm | G313: =IF(BD!$E313="","",(E313/(H313*I313))) | H313: 1 | I313: 100 | J313: =CONCATENATE(LEFT(C313,1),MID(C313,SEARCH("_",C313)+1,2),TEXT(A313,"000")) -> SME128
A314: 128 | B314: FIBRA TERMIADERIBLE CONTRAFUERTE _ | C314: SECUNDARIO_MEDULAR | D314: m | F314: cm | G314: =IF(BD!$E314="","",(E314/(H314*I314))) | H314: 1 | I314: 100 | J314: =CONCATENATE(LEFT(C314,1),MID(C314,SEARCH("_",C314)+1,2),TEXT(A314,"000")) -> SME128
A315: 128 | B315: FIBRA TERMIADERIBLE puntra 1.5 mm _ | C315: SECUNDARIO_MEDULAR | D315: m | F315: cm | G315: =IF(BD!$E315="","",(E315/(H315*I315))) | H315: 1 | I315: 100 | J315: =CONCATENATE(LEFT(C315,1),MID(C315,SEARCH("_",C315)+1,2),TEXT(A315,"000")) -> SME128
A316: 128 | B316: FIBRA PLANTILLA 1.5 mm GRIS _ | C316: SECUNDARIO_MEDULAR | D316: m | F316: cm | G316: =IF(BD!$E316="","",(E316/(H316*I316))) | H316: 1 | I316: 100 | J316: =CONCATENATE(LEFT(C316,1),MID(C316,SEARCH("_",C316)+1,2),TEXT(A316,"000")) -> SME128
A317: 85 | B317: HILO ENCERADO | C317: SECUNDARIO_MEDULAR | D317: m | E317: 7000 | F317: Cono | G317: =IF(BD!$E317="","",(E317/(H317*I317))) -> 7000 | H317: 1 | I317: 1 | J317: =CONCATENATE(LEFT(C317,1),MID(C317,SEARCH("_",C317)+1,2),TEXT(A317,"000")) -> SME085
A318: 128 | B318: HILO ENCERADO AMARILLO _ CONO | C318: SECUNDARIO_MEDULAR | D318: m | F318: cm | G318: =IF(BD!$E318="","",(E318/(H318*I318))) | H318: 1 | I318: 100 | J318: =CONCATENATE(LEFT(C318,1),MID(C318,SEARCH("_",C318)+1,2),TEXT(A318,"000")) -> SME128
A319: 128 | B319: HILO ENCERADO BLANCO _ CONO | C319: SECUNDARIO_MEDULAR | D319: m | F319: cm | G319: =IF(BD!$E319="","",(E319/(H319*I319))) | H319: 1 | I319: 100 | J319: =CONCATENATE(LEFT(C319,1),MID(C319,SEARCH("_",C319)+1,2),TEXT(A319,"000")) -> SME128
A320: 128 | B320: HILO ENCERADO MORADO _ CONO | C320: SECUNDARIO_MEDULAR | D320: m | F320: cm | G320: =IF(BD!$E320="","",(E320/(H320*I320))) | H320: 1 | I320: 100 | J320: =CONCATENATE(LEFT(C320,1),MID(C320,SEARCH("_",C320)+1,2),TEXT(A320,"000")) -> SME128
A321: 128 | B321: HILO ENCERADO NEGRO _ CONO | C321: SECUNDARIO_MEDULAR | D321: m | F321: cm | G321: =IF(BD!$E321="","",(E321/(H321*I321))) | H321: 1 | I321: 100 | J321: =CONCATENATE(LEFT(C321,1),MID(C321,SEARCH("_",C321)+1,2),TEXT(A321,"000")) -> SME128
A322: 128 | B322: HILO ENCERADO ROJO _ CONO | C322: SECUNDARIO_MEDULAR | D322: m | F322: cm | G322: =IF(BD!$E322="","",(E322/(H322*I322))) | H322: 1 | I322: 100 | J322: =CONCATENATE(LEFT(C322,1),MID(C322,SEARCH("_",C322)+1,2),TEXT(A322,"000")) -> SME128
A323: 128 | B323: HILO ENCERADO VERDE FLUORECENTE _ CONO | C323: SECUNDARIO_MEDULAR | D323: m | F323: cm | G323: =IF(BD!$E323="","",(E323/(H323*I323))) | H323: 1 | I323: 100 | J323: =CONCATENATE(LEFT(C323,1),MID(C323,SEARCH("_",C323)+1,2),TEXT(A323,"000")) -> SME128
A324: 128 | B324: HILO ENCERADO VERDE OSCURO _ CONO | C324: SECUNDARIO_MEDULAR | D324: m | F324: cm | G324: =IF(BD!$E324="","",(E324/(H324*I324))) | H324: 1 | I324: 100 | J324: =CONCATENATE(LEFT(C324,1),MID(C324,SEARCH("_",C324)+1,2),TEXT(A324,"000")) -> SME128
A325: 86 | B325: HILO ITALIANO | C325: SECUNDARIO_MEDULAR | D325: Rollo | E325: 12000 | F325: Cono | G325: =IF(BD!$E325="","",(E325/(H325*I325))) -> 12000 | H325: 1 | I325: 1 | J325: =CONCATENATE(LEFT(C325,1),MID(C325,SEARCH("_",C325)+1,2),TEXT(A325,"000")) -> SME086
A326: 87 | B326: HILO NYLON #20 | C326: SECUNDARIO_MEDULAR | D326: U | E326: 7266.6667 | F326: Cono | G326: =IF(BD!$E326="","",(E326/(H326*I326))) -> 7266.6667 | H326: 1 | I326: 1 | J326: =CONCATENATE(LEFT(C326,1),MID(C326,SEARCH("_",C326)+1,2),TEXT(A326,"000")) -> SME087
A327: 88 | B327: HILO NYLON #40 | C327: SECUNDARIO_MEDULAR | D327: U | E327: 7266.6667 | F327: Cono | G327: =IF(BD!$E327="","",(E327/(H327*I327))) -> 7266.6667 | H327: 1 | I327: 1 | J327: =CONCATENATE(LEFT(C327,1),MID(C327,SEARCH("_",C327)+1,2),TEXT(A327,"000")) -> SME088
A328: 89 | B328: HILO NYLON #60 | C328: SECUNDARIO_MEDULAR | D328: U | E328: 7266.665 | F328: Cono | G328: =IF(BD!$E328="","",(E328/(H328*I328))) -> 7266.665 | H328: 1 | I328: 1 | J328: =CONCATENATE(LEFT(C328,1),MID(C328,SEARCH("_",C328)+1,2),TEXT(A328,"000")) -> SME089
A329: 90 | B329: HILO TERLENKA | C329: SECUNDARIO_MEDULAR | D329: Rollo | E329: 5000 | F329: Cono | G329: =IF(BD!$E329="","",(E329/(H329*I329))) -> 5000 | H329: 1 | I329: 1 | J329: =CONCATENATE(LEFT(C329,1),MID(C329,SEARCH("_",C329)+1,2),TEXT(A329,"000")) -> SME090
A330: 128 | B330: HILOS N°20 beige de 250 m | C330: SECUNDARIO_MEDULAR | D330: m | F330: cm | G330: =IF(BD!$E330="","",(E330/(H330*I330))) | H330: 1 | I330: 100 | J330: =CONCATENATE(LEFT(C330,1),MID(C330,SEARCH("_",C330)+1,2),TEXT(A330,"000")) -> SME128
A331: 128 | B331: HILOS N°20 Blanco de 250 m | C331: SECUNDARIO_MEDULAR | D331: m | F331: cm | G331: =IF(BD!$E331="","",(E331/(H331*I331))) | H331: 1 | I331: 100 | J331: =CONCATENATE(LEFT(C331,1),MID(C331,SEARCH("_",C331)+1,2),TEXT(A331,"000")) -> SME128
A332: 128 | B332: HILOS N°20 Café de 250 m | C332: SECUNDARIO_MEDULAR | D332: m | F332: cm | G332: =IF(BD!$E332="","",(E332/(H332*I332))) | H332: 1 | I332: 100 | J332: =CONCATENATE(LEFT(C332,1),MID(C332,SEARCH("_",C332)+1,2),TEXT(A332,"000")) -> SME128
...

Sheet Listas
D1: Destinación | F1: Programas | H1: Instructores | I1: Documento | K1: Observaciones | M1: Categorias | Z1: Lis
A2: Nombre de la Unidades | B2: Simbololo de la Unidad | D2: Columna1 | F2: COMPLEMENTARIO CALZADO | H2: Alexander Marulanda Bedoya | I2: 71765586 | K2: Restar_Pedido | M2: ADHESIVOS_Solventes
A3: Caja | B3: Caja | D3: Calzado Formación | F3: COMPLEMENTARIO MARROQUINERIA | H3: Alexander Ortega Ortiz | I3: 76322427 | K3: Amarillo | M3: CUERO
A4: centimetros | B4: cm | D4: Calzado Producción | F4: EL.ART. PROD. CUERO | H4: Alina Posada Villada | I4: 43687423 | K4: Azul | M4: HERRAJES
A5: centimetros cuadrados | B5: cm2 | D5: Marroquinería Formación | F5: GUARNICION CALZADO | H5: Carlos Cruz Vasquez | I5: 3353808 | K5: Blanco | M5: HERRAMIENTAS_
A6: Cono | B6: Cono | D6: Marroquinería Producción | F6: MODELAJE CALZADO | H6: Carlos Hincapie Monsalve | I6: 1036620040 | K6: Café | M6: INSUMOS_COMPL_
A7: decimetros | B7: dm | D7: Muestras | F7: MODELAJE MARROQUINERIA | H7: Carlos Mario Castañeda M | I7: 71387261 | K7: Colores Surtidos | M7: SECUNDARIO_MEDULAR
A8: decimetros Cuadrados | B8: dm2 | D8: Transversal | F8: PRODCCION CALZADO | H8: Cindy Rodriguez Armesto | I8: 1033686182 | K8: Colores Varios | M8: SiNTETICOS_TEXTILES
A9: Frasco | B9: F | F9: PRODCCION CALZADO Y MARROQUINERIA | H9: Deisy Catalina Guisao | I9: 1128272231 | K9: Negro | M9: SUELAS
A10: Galon | B10: gal | F10: PRODUCCION MARROQUINERIA | H10: Diana Gutiérrez Bolívar | I10: 32209568 | K10: Rojo | M10: FORMACION
A11: Garrafa | B11: gf | F11: MANTAJE Y ENSUELADO | H11: Diego Gomez Chavarria | I11: 71292446 | K11: Verde | M11: PAPELERIA_P
A12: gramos | B12: g | H12: Dyron Javier Ramirez Osorio | I12: 98577544 | M12: QUÍMICOS
A13: Hoja | B13: Hoja | H13: Elizaveth Mancera Escobar | I13: 52714421
A14: kilogramo | B14: kg | H14: Elkin Zuelta Montoya | I14: 70323724
A15: kit | B15: kit | H15: Emely Rivera Delgado | I15: 32142539
A16: Lamina | B16: Lámina | H16: Fredy Calderón Lozano | I16: 79897894
A17: Libra | B17: lb | H17: Gloria Pabon Yepes | I17: 32184975
A18: Litro | B18: l | H18: Jorge Hernandez Cano | I18: 70512283
A19: metros | B19: m | H19: Jorge Mario Correa Castañeda | I19: 16757142
A20: miligramos | B20: mg | H20: Juan Hoyos Maya | I20: 1152194903
A21: mililitro | B21: ml | H21: Juan Velásquez Rivas | I21: 3396236
A22: Ovillo | B22: Ovillo | H22: Juan Villa Salazar | I22: 71639999
A23: Paquetre | B23: paq | H23: Juan Vivas Alarcon | I23: 1121878447
A24: pares | B24: Par | H24: Luis Fernando Velásquez | I24: 71649025
A25: Pliego | B25: Pliego | H25: María Bolivar Agudelo | I25: 43506380
A26: Resma | B26: Resma | H26: Maribel Gil Zapata | I26: 43498846
A27: Rollo | B27: Rollo | H27: Maybelline Aristizabal | I27: 1128404319
A28: Unidad | B28: U | H28: Orlando Bolaños Carlosama | I28: 80902330
H29: Paul Tamayo Caviedes | I29: 5820573
H30: Ronald Quintero Aguilera | I30: 80810881
H31: Rubén Patiño Ospina | I31: 70566616
H32: Samuel Hernandez Alvarez | I32: 71765633
H33: Sebastian Tabares Osuna | I33: 1040733121
H34: Sofia Delgado Monsalve | I34: 37841713
H35: Susana Castaño Tirado | I35: 43874217
