Workbook
Name ADHESIVOS_Solventes: BD!$B$8:$B$18
Name AdheySol: BD!$B$7
Name Aux_Med: BD!$B$104
Name CATEGORIAS: Listas!$I$2:$I$12
Name Cuer_: BD!$B$401
Name CUERO: BD!$B$402:$B$424
Name Herraj_: BD!$B$444
Name HERRAJES: BD!$B$445:$B$886
Name Herram_: BD!$B$946
Name HERRAMIENTAS_: Tabla13[Material]
Name INSUMOS_COMPL_: BD!$B$985:$B$1021
Name Materiales: BD!$B$6:$B$1200
Name Observaciones: Listas!$G$2:$G$12
Name quimic_: BD!$B$1056
Name QUÍMICOS: BD!$B$1057:$B$1123
Name SECUNDARIO: BD!$B$105:$B$218
Name Sin_Tex: BD!$B$893
Name SiNTETICOS_TEXTILES: BD!$B$894:$B$925
Name SUELAS: Tabla5[Material]
Name T_comp_Aux_AD: BD!$A$8:$J$18
Name Tabla_Completa: BD!$A$6:'BD'!$J$1200
Name Total_AdhySol: BD!$B$6
Name Total_Cuero: BD!$B$400
Name Total_Herrajes: BD!$B$443
Name Total_Herramientas: BD!$B$945
Name Total_Ins_Compl: BD!$B$983
Name Total_SECUNDARIO_MEDULAR: BD!$B$103
Name Total_Sint_y_Tex: BD!$B$892
Name Unidades: Listas!$B$3:$B$28

Sheet Solicitar
A1: NOMBRE DEL PRODUCTO | E1: Bota 1 | L1: FECHA DE ELABORACION | O1: 45936
A2: VALOR DE UNA UNIDAD ($) | D2: =IF(K2="","",(SUM(W7:Y25)-(SUMIF(U7:V25,"Restar_Pedido",W7:Y25)))/$K$2) -> 33432.466 | G2: CANTIDAD A PRODUCIR | K2: 1 | M2: VALOR PRODUCCION($) | O2: =IFERROR(IF(K2=0,"",D2*K2),"") -> 33432.466
A4: Categoria del Insumo | D4: MATERIALES E INSUMOS. | O4: UNIDAD DE MEDIDA | Q4: CANTIDAD PEDIDA para: Un solo producto
S5: Ayuda de Cálculo | V5: =IF(K2="","",1/K2) -> 1 | X5: 1 | Y5: =IFERROR((V5*X5)," ") -> 1
S6: Entregar | U6: Observaciones | W6: Valor materiales (S)
A7: CUERO | D7: NOBUCK | O7: =IFERROR(IF(D7="","",INDEX(Tabla_Completa,MATCH(D7,Materiales,0),6)),"") -> dm2 | Q7: 1.4 | S7: =IFERROR(IF(Q7="Unidad","1",(Q7*$K$2)),"") -> 1.4 | U7: morado | W7: =IFERROR(IF(D7="","",INDEX(Tabla_Completa,MATCH(Solicitar!D7,Materiales,0),7)*S7),"") -> 1680
A8: CUERO | D8: NOBUCK | O8: =IFERROR(IF(D8="","",INDEX(Tabla_Completa,MATCH(D8,Materiales,0),6)),"") -> dm2 | Q8: 1.7 | S8: =IFERROR(IF(Q8="Unidad","1",(Q8*$K$2)),"") -> 1.7 | U8: negro | W8: =IFERROR(IF(D8="","",INDEX(Tabla_Completa,MATCH(Solicitar!D8,Materiales,0),7)*S8),"") -> 2040
A9: SiNTETICOS_TEXTILES | D9: FORRO PIQUET | O9: =IFERROR(IF(D9="","",INDEX(Tabla_Completa,MATCH(D9,Materiales,0),6)),"") -> cm2 | Q9: 2.6 | S9: =IFERROR(IF(Q9="Unidad","1",(Q9*$K$2)),"") -> 2.6 | U9: Negro | W9: =IFERROR(IF(D9="","",INDEX(Tabla_Completa,MATCH(Solicitar!D9,Materiales,0),7)*S9),"") -> 5.2029714
A10: SECUNDARIO | D10: ESPUMA MULTIFORM DENSIDAD 40 DE 5 mm | O10: =IFERROR(IF(D10="","",INDEX(Tabla_Completa,MATCH(D10,Materiales,0),6)),"") -> cm2 | Q10: 1.6 | S10: =IFERROR(IF(Q10="Unidad","1",(Q10*$K$2)),"") -> 1.6 | W10: =IFERROR(IF(D10="","",INDEX(Tabla_Completa,MATCH(Solicitar!D10,Materiales,0),7)*S10),"") -> 1.6
A11: SECUNDARIO | D11: HILO NYLON #40 | O11: =IFERROR(IF(D11="","",INDEX(Tabla_Completa,MATCH(D11,Materiales,0),6)),"") -> Cono | Q11: 1 | S11: =IFERROR(IF(Q11="Unidad","1",(Q11*$K$2)),"") -> 1 | U11: Negro | W11: =IFERROR(IF(D11="","",INDEX(Tabla_Completa,MATCH(Solicitar!D11,Materiales,0),7)*S11),"") -> 7266.6667
A12: SECUNDARIO | D12: HILO NYLON #40 | O12: =IFERROR(IF(D12="","",INDEX(Tabla_Completa,MATCH(D12,Materiales,0),6)),"") -> Cono | Q12: 1 | S12: =IFERROR(IF(Q12="Unidad","1",(Q12*$K$2)),"") -> 1 | U12: verde | W12: =IFERROR(IF(D12="","",INDEX(Tabla_Completa,MATCH(Solicitar!D12,Materiales,0),7)*S12),"") -> 7266.6667
A13: SECUNDARIO | D13: HILO NYLON #60 | O13: =IFERROR(IF(D13="","",INDEX(Tabla_Completa,MATCH(D13,Materiales,0),6)),"") -> Cono | Q13: 1 | S13: =IFERROR(IF(Q13="Unidad","1",(Q13*$K$2)),"") -> 1 | U13: negro | W13: =IFERROR(IF(D13="","",INDEX(Tabla_Completa,MATCH(Solicitar!D13,Materiales,0),7)*S13),"") -> 7266.665
A14: SECUNDARIO | D14: HILO NYLON #60 | O14: =IFERROR(IF(D14="","",INDEX(Tabla_Completa,MATCH(D14,Materiales,0),6)),"") -> Cono | Q14: 1 | S14: =IFERROR(IF(Q14="Unidad","1",(Q14*$K$2)),"") -> 1 | U14: verde | W14: =IFERROR(IF(D14="","",INDEX(Tabla_Completa,MATCH(Solicitar!D14,Materiales,0),7)*S14),"") -> 7266.665
A15: SECUNDARIO | D15: CORDON ENCERADO NEGRO LARGO | O15: =IFERROR(IF(D15="","",INDEX(Tabla_Completa,MATCH(D15,Materiales,0),6)),"") -> Par | Q15: 1 | S15: =IFERROR(IF(Q15="Unidad","1",(Q15*$K$2)),"") -> 1 | W15: =IFERROR(IF(D15="","",INDEX(Tabla_Completa,MATCH(Solicitar!D15,Materiales,0),7)*S15),"") -> 639
O16: =IFERROR(IF(D16="","",INDEX(Tabla_Completa,MATCH(D16,Materiales,0),6)),"") | S16: =IFERROR(IF(Q16="Unidad","1",(Q16*$K$2)),"") -> 0 | W16: =IFERROR(IF(D16="","",INDEX(Tabla_Completa,MATCH(Solicitar!D16,Materiales,0),7)*S16),"")
O17: =IFERROR(IF(D17="","",INDEX(Tabla_Completa,MATCH(D17,Materiales,0),6)),"") | S17: =IFERROR(IF(Q17="Unidad","1",(Q17*$K$2)),"") -> 0 | W17: =IFERROR(IF(D17="","",INDEX(Tabla_Completa,MATCH(Solicitar!D17,Materiales,0),7)*S17),"")
O18: =IFERROR(IF(D18="","",INDEX(Tabla_Completa,MATCH(D18,Materiales,0),6)),"") | S18: =IFERROR(IF(Q18="Unidad","1",(Q18*$K$2)),"") -> 0 | W18: =IFERROR(IF(D18="","",INDEX(Tabla_Completa,MATCH(Solicitar!D18,Materiales,0),7)*S18),"")
O19: =IFERROR(IF(D19="","",INDEX(Tabla_Completa,MATCH(D19,Materiales,0),6)),"") | S19: =IFERROR(IF(Q19="Unidad","1",(Q19*$K$2)),"") -> 0 | W19: =IFERROR(IF(D19="","",INDEX(Tabla_Completa,MATCH(Solicitar!D19,Materiales,0),7)*S19),"")
O20: =IFERROR(IF(D20="","",INDEX(Tabla_Completa,MATCH(D20,Materiales,0),6)),"") | S20: =IFERROR(IF(Q20="Unidad","1",(Q20*$K$2)),"") -> 0 | W20: =IFERROR(IF(D20="","",INDEX(Tabla_Completa,MATCH(Solicitar!D20,Materiales,0),7)*S20),"")
O21: =IFERROR(IF(D21="","",INDEX(Tabla_Completa,MATCH(D21,Materiales,0),6)),"") | S21: =IFERROR(IF(Q21="Unidad","1",(Q21*$K$2)),"") -> 0 | W21: =IFERROR(IF(D21="","",INDEX(Tabla_Completa,MATCH(Solicitar!D21,Materiales,0),7)*S21),"")
O22: =IFERROR(IF(D22="","",INDEX(Tabla_Completa,MATCH(D22,Materiales,0),6)),"") | S22: =IFERROR(IF(Q22="Unidad","1",(Q22*$K$2)),"") -> 0 | W22: =IFERROR(IF(D22="","",INDEX(Tabla_Completa,MATCH(Solicitar!D22,Materiales,0),7)*S22),"")
O23: =IFERROR(IF(D23="","",INDEX(Tabla_Completa,MATCH(D23,Materiales,0),6)),"") | S23: =IFERROR(IF(Q23="Unidad","1",(Q23*$K$2)),"") -> 0 | W23: =IFERROR(IF(D23="","",INDEX(Tabla_Completa,MATCH(Solicitar!D23,Materiales,0),7)*S23),"")
O24: =IFERROR(IF(D24="","",INDEX(Tabla_Completa,MATCH(D24,Materiales,0),6)),"") | S24: =IFERROR(IF(Q24="Unidad","1",(Q24*$K$2)),"") -> 0 | W24: =IFERROR(IF(D24="","",INDEX(Tabla_Completa,MATCH(Solicitar!D24,Materiales,0),7)*S24),"")
O25: =IFERROR(IF(D25="","",INDEX(Tabla_Completa,MATCH(D25,Materiales,0),6)),"") | S25: =IFERROR(IF(Q25="Unidad","1",(Q25*$K$2)),"") -> 0 | W25: =IFERROR(IF(D25="","",INDEX(Tabla_Completa,MATCH(Solicitar!D25,Materiales,0),7)*S25),"")
O26: =IFERROR(IF(D26="","",INDEX(Tabla_Completa,MATCH(D26,Materiales,0),6)),"") | S26: =IFERROR(IF(Q26="Unidad","1",(Q26*$K$2)),"") -> 0 | W26: =IFERROR(IF(D26="","",INDEX(Tabla_Completa,MATCH(Solicitar!D26,Materiales,0),7)*S26),"")
O27: =IFERROR(IF(D27="","",INDEX(Tabla_Completa,MATCH(D27,Materiales,0),6)),"") | S27: =IFERROR(IF(Q27="Unidad","1",(Q27*$K$2)),"") -> 0 | W27: =IFERROR(IF(D27="","",INDEX(Tabla_Completa,MATCH(Solicitar!D27,Materiales,0),7)*S27),"")
O28: =IFERROR(IF(D28="","",INDEX(Tabla_Completa,MATCH(D28,Materiales,0),6)),"") | S28: =IFERROR(IF(Q28="Unidad","1",(Q28*$K$2)),"") -> 0 | W28: =IFERROR(IF(D28="","",INDEX(Tabla_Completa,MATCH(Solicitar!D28,Materiales,0),7)*S28),"")
A36: Recomendación:
A37: Insertar Imagen: en la ruta: Insertar/Ilustraciones/Imágenes/en este dispositivo
A41: Instrucciones Generales | N41: ADHESIVOS_Solventes | R41: Todo lo relacionado con adhesivos, incluido los solventes
A42: Los campos en color naranja son obligatorios, se deben registrar | N42: SECUNDARIO | R42: Todos los insumos que hacen parte del producto, en un nivel secundario, o que van en la parte interna de los productos. Ejm Cordones
A43: Los campos de este color en la parte de debajo o a un lado significa que tiene una lista desplegable | N43: CUERO | R43: Solo insumos bajo esta categoría
A44: Los campos en color gris oscuro y claro,son campos que no permiten edición( estan Bloqueados) | N44: HERRAJES | R44: Todos los insumos que cumplen esta condición
A45: Para ingresar la fecha, solo digite asi: tecla CTRL + tecla de punto y coma(;) | N45: HERRAMIENTAS | R45: Todos los elementos necesarios para desarrollar el proceso, estos no deben hacer parte del costo
A46: Leer cada una de las casillas con notas, como ayuda para el correcto llenado de datos | N46: INSUMOS_COMPlementarios | R46: Todos los insumos necesarios en elproceso del producto pero que no quedan dentro del producto ( ejm Agujas)
N47: PAPELERIA_P | R47: Todos los elementos que cumplen esta condición
N48: SiNTETICOS_TEXTILES | R48: Todos los insumos utilizados altenativos al cuero o forro
N49: SUELAS | R49: Todos los insumos que cumplen esta condición

Sheet BD
Z1: Bede
E3: =SUM(Total_AdhySol,Total_SECUNDARIO_MEDULAR,Total_Cuero,Total_Herrajes,Total_Sint_y_Tex,Total_Herramientas,Total_Ins_Compl) -> 660
A6: Totales | B6: =SUBTOTAL(3,(BD!$B$8:$B$18)) -> 11 | H6: Magnitudes para calculo minimo
A7: Item | B7: Material | C7: Categoría | D7: Unidad de Compra Almacen | E7: Precio Unidad de Compra ( $) | F7: Unidad Despacho Almacen | G7: Valor /U Despacho en Almacen | H7: Magnitud 1 en U | I7: Magnitud 2 en U | J7: Columna1 | K7: Columna2
A8: 1 | B8: ADHESIVO PU | C8: ADHESIVOS_Solventes | D8: gal | E8: 74650 | F8: ml | G8: =IF(BD!$E8="","",(E8/(H8*I8))) -> 19.722589 | H8: 3785 | I8: 1
A9: =A8+1 -> 2 | B9: AQUAPREN CALZADO Y MARROQUINERÍA SPRAY | C9: ADHESIVOS_Solventes | D9: gal | E9: 231671.5 | F9: ml | G9: =IF(BD!$E9="","",(E9/(H9*I9))) -> 61.207794 | H9: 3785 | I9: 1
A10: =A9+1 -> 3 | B10: AQUAPREN GUARNECIDA | C10: ADHESIVOS_Solventes | D10: gal | E10: 231671.5 | F10: ml | G10: =IF(BD!$E10="","",(E10/(H10*I10))) -> 61.207794 | H10: 3785 | I10: 1
A11: =A10+1 -> 4 | B11: CARDA RAPIDO | C11: ADHESIVOS_Solventes | D11: gal | E11: 78666.625 | F11: ml | G11: =IF(BD!$E11="","",(E11/(H11*I11))) -> 20.783785 | H11: 3785 | I11: 1
A12: =A11+1 -> 5 | B12: DILUSOR DE PINTURA 2-THIN | C12: ADHESIVOS_Solventes | D12: U | E12: 72665 | F12: U | G12: =IF(BD!$E12="","",(E12/(H12*I12))) -> 72665 | H12: 1 | I12: 1
A13: =A12+1 -> 6 | B13: HALOGENANTE | C13: ADHESIVOS_Solventes | D13: gal | E13: 59690.625 | F13: ml | G13: =IF(BD!$E13="","",(E13/(H13*I13))) -> 15.77031 | H13: 3785 | I13: 1
A14: =A13+1 -> 7 | B14: LIMPIADOR DE SUELAS | C14: ADHESIVOS_Solventes | D14: gal | E14: 50200 | F14: ml | G14: =IF(BD!$E14="","",(E14/(H14*I14))) -> 13.26288 | H14: 3785 | I14: 1
A15: =A14+1 -> 8 | B15: PEGANTE CEMENTO DE CONTACTO BASE CLOROPRENO | C15: ADHESIVOS_Solventes | D15: gal | E15: 66108 | F15: ml | G15: =IF(BD!$E15="","",(E15/(H15*I15))) -> 17.465786 | H15: 3785 | I15: 1
A16: =A15+1 -> 9 | B16: PRIMER PU | C16: ADHESIVOS_Solventes | D16: gal | E16: 61960 | F16: ml | G16: =IF(BD!$E16="","",(E16/(H16*I16))) -> 16.369881 | H16: 3785 | I16: 1
A17: =A16+1 -> 10 | B17: SOLUCIÓN DE CAUCHO | C17: ADHESIVOS_Solventes | D17: gal | E17: 28400 | F17: ml | G17: =IF(BD!$E17="","",(E17/(H17*I17))) -> 7.5033025 | H17: 3785 | I17: 1
A18: =A17+1 -> 11 | B18: THINNER | C18: ADHESIVOS_Solventes | D18: gal | E18: 36816 | F18: gal | G18: =IF(BD!$E18="","",(E18/(H18*I18))) -> 36816 | H18: 1 | I18: 1
B55: Insertar Filas!!
B100: Insertar Filas!!
A103: Totales | B103: =SUBTOTAL(3,(B105:B218)) -> 114
A104: Item | B104: Material | C104: Categoría | D104: Unidad de Compra Almacen | E104: Precio Unidad de Compra ( $) | F104: Unidad Despacho Almacen | G104: Valor /U Despacho en Almacen | H104: Magnitud 1 en U | I104: Magnitud 2 en U | J104: Columna1 | K104: Columna2
A105: 1 | B105: CAMBRIÓN | C105: SECUNDARIO | D105: Par | E105: 760 | F105: Par | G105: =IF(BD!$E105="","",(E105/(H105*I105))) -> 760 | H105: 1 | I105: 1
A106: 2 | B106: CAUCHO LATEX | C106: SECUNDARIO | D106: Lámina | E106: 45667 | F106: Lámina | G106: =IF(BD!$E106="","",(E106/(H106*I106))) -> 45667 | H106: 1 | I106: 1
A107: 3 | B107: CINTA FALLA _RIBETE 18 mm CON APRESTO #3 | C107: SECUNDARIO | D107: Rollo | E107: 41000 | F107: m | G107: =IF(BD!$E107="","",(E107/(H107*I107))) -> 410 | H107: 100 | I107: 1
A108: 4 | B108: CINTA FALLA _RIBETE 24 mm CON APRESTO #5 | C108: SECUNDARIO | D108: Rollo | E108: 58500 | F108: m | G108: =IF(BD!$E108="","",(E108/(H108*I108))) -> 585 | H108: 100 | I108: 1
A109: 5 | B109: COMFORTEX CALIBRE 1.5mm. | C109: SECUNDARIO | D109: Lámina | E109: 17830 | F109: cm2 | G109: =IF(BD!$E109="","",(E109/(H109*I109))) -> 1.2735714 | H109: 140 | I109: 100
A110: 42 | B110: Cordon ENCERADO NEGRO 110cm | C110: SECUNDARIO | D110: Par | E110: 639 | F110: Par | G110: =IF(BD!$E110="","",(E110/(H110*I110))) -> 639 | H110: 1 | I110: 1
A111: 43 | B111: CORDON ENCERADO NEGRO LARGO | C111: SECUNDARIO | D111: Par | E111: 639 | F111: Par | G111: =IF(BD!$E111="","",(E111/(H111*I111))) -> 639 | H111: 1 | I111: 1
A112: 44 | B112: CORDON ENCERADO PLANO CAFE | C112: SECUNDARIO | D112: Par | E112: 639 | F112: Par | G112: =IF(BD!$E112="","",(E112/(H112*I112))) -> 639 | H112: 1 | I112: 1
A113: 45 | B113: CORDON ENCERADO PLANO NEGRO | C113: SECUNDARIO | D113: Par | E113: 639 | F113: Par | G113: =IF(BD!$E113="","",(E113/(H113*I113))) -> 639 | H113: 1 | I113: 1
A114: 46 | B114: CORDON ENCERADO REDODNDO CAFE | C114: SECUNDARIO | D114: Par | E114: 639 | F114: Par | G114: =IF(BD!$E114="","",(E114/(H114*I114))) -> 639 | H114: 1 | I114: 1
A115: 47 | B115: CORDON NEGRO PLANO | C115: SECUNDARIO | D115: Par | E115: 639 | F115: Par | G115: =IF(BD!$E115="","",(E115/(H115*I115))) -> 639 | H115: 1 | I115: 1
A116: 48 | B116: CORDON NEGRO REDONDO | C116: SECUNDARIO | D116: Par | E116: 639 | F116: Par | G116: =IF(BD!$E116="","",(E116/(H116*I116))) -> 639 | H116: 1 | I116: 1
... A218: 128 | B218: YUMBOLON 4mm (CM²) | C218: SECUNDARIO | D218: m | E218: 10780 | F218: cm2 | G218: =IF(BD!$E218="","",(E218/(H218*I218))) -> 0.77 | H218: 140 | I218: 100
B398: Insertar Filas!!
A400: Totales | B400: =SUBTOTAL(3,(B402:B424)) -> 23
A401: Item | B401: Material | C401: Categoría | D401: Unidad de Compra Almacen | E401: Precio Unidad de Compra ( $) | F401: Unidad Despacho Almacen | G401: Valor /U Despacho en Almacen | H401: Magnitud 1 en U | I401: Magnitud 2 en U | J401: Columna1 | K401: Columna2
A402: 1 | B402: CARNAZA | C402: CUERO | D402: dm2 | E402: 380 | F402: dm2 | G402: =IF(BD!$E402="","",(E402/(H402*I402))) -> 380 | H402: 1 | I402: 1
A403: =A402+1 -> 2 | B403: CONFECCION | C403: CUERO | D403: dm2 | E403: 848.47 | F403: dm2 | G403: =IF(BD!$E404="","",(E403/(H403*I403))) -> 848.47 | H403: 1 | I403: 1
A404: =A403+1 -> 3 | B404: CUERO ARIZONA | C404: CUERO | D404: dm2 | E404: 815 | F404: dm2 | G404: =IF(BD!$E406="","",(E404/(H404*I404))) -> 815 | H404: 1 | I404: 1
A405: =A404+1 -> 4 | B405: CUERO CROSTA | C405: CUERO | D405: dm2 | E405: 623.66667 | F405: dm2 | G405: =IF(BD!$E407="","",(E405/(H405*I405))) -> 623.66667 | H405: 1 | I405: 1
A406: =A405+1 -> 5 | B406: CUERO CRUST | C406: CUERO | D406: dm2 | E406: 698.53 | F406: dm2 | G406: =IF(BD!$E405="","",(E406/(H406*I406))) -> 698.53 | H406: 1 | I406: 1
A407: =A406+1 -> 6 | B407: CUERO FORRO BADANA | C407: CUERO | D407: dm2 | E407: 390.66667 | F407: dm2 | G407: =IF(BD!$E406="","",(E407/(H407*I407))) -> 390.66667 | H407: 1 | I407: 1
A408: =A407+1 -> 7 | B408: CUERO FORRO CERDO | C408: CUERO | D408: dm2 | E408: 477.19 | F408: dm2 | G408: =IF(BD!$E407="","",(E408/(H408*I408))) -> 477.19 | H408: 1 | I408: 1
A409: =A408+1 -> 8 | B409: CUERO GRASO | C409: CUERO | D409: dm2 | E409: 998.41 | F409: dm2 | G409: =IF(BD!$E408="","",(E409/(H409*I409))) -> 998.41 | H409: 1 | I409: 1
A410: =A409+1 -> 9 | B410: CUERO NAPA CON CERA Y ACABADO ESPEJO | C410: CUERO | D410: dm2 | E410: 898.45 | F410: dm2 | G410: =IF(BD!$E409="","",(E410/(H410*I410))) -> 898.45 | H410: 1 | I410: 1
A411: =A410+1 -> 10 | B411: CUERO PELO | C411: CUERO | D411: dm2 | E411: 1500 | F411: dm2 | G411: =IF(BD!$E410="","",(E411/(H411*I411))) -> 1500 | H411: 1 | I411: 1
A412: =A411+1 -> 11 | B412: CUERO PERGAMINO | C412: CUERO | D412: dm2 | E412: 53371.5 | F412: dm2 | G412: =IF(BD!$E411="","",(E412/(H412*I412))) -> 53371.5 | H412: 1 | I412: 1
A413: =A412+1 -> 12 | B413: CUERO SOFTY | C413: CUERO | D413: dm2 | E413: 897.26 | F413: dm2 | G413: =IF(BD!$E412="","",(E413/(H413*I413))) -> 897.26 | H413: 1 | I413: 1
A414: =A413+1 -> 13 | B414: CUERO TALA #2 | C414: CUERO | D414: dm2 | E414: 1673.3335 | F414: dm2 | G414: =IF(BD!$E413="","",(E414/(H414*I414))) -> 1673.3335 | H414: 1 | I414: 1
A415: =A414+1 -> 14 | B415: DOTACION | C415: CUERO | D415: dm2 | E415: 250 | F415: dm2 | G415: =IF(BD!$E414="","",(E415/(H415*I415))) -> 250 | H415: 1 | I415: 1
A416: =A415+1 -> 15 | B416: FOLIA | C416: CUERO | D416: dm2 | E416: 898.45 | F416: dm2 | G416: =IF(BD!$E415="","",(E416/(H416*I416))) -> 898.45 | H416: 1 | I416: 1
A417: =A416+1 -> 16 | B417: FOLIA BRILLANTE | C417: CUERO | D417: dm2 | E417: 898.45 | F417: dm2 | G417: =IF(BD!$E416="","",(E417/(H417*I417))) -> 898.45 | H417: 1 | I417: 1
... A424: =A423+1 -> 23 | B424: TALA | C424: CUERO | D424: dm2 | E424: 759.22 | F424: dm2 | G424: =IF(BD!$E423="","",(E424/(H424*I424))) -> 759.22 | H424: 1 | I424: 1
B441: Insertar Filas!!
A443: Totales | B443: =SUBTOTAL(3,(B445:B865)) -> 421
A444: Item | B444: Material | C444: Categoría | D444: Unidad de Compra Almacen | E444: Precio Unidad de Compra ( $) | F444: Unidad Despacho Almacen | G444: Valor /U Despacho en Almacen | H444: Magnitud 1 en U | I444: Magnitud 2 en U | J444: Columna1 | K444: Columna2
A445: 1 | B445: ARANDELA PLANA PAVONADA 1"ZAMAC | C445: HERRAJES | D445: U | E445: 304.64 | F445: U | G445: =IF(BD!$E444="","",(E445/(H445*I445))) -> 304.64 | H445: 1 | I445: 1
A446: =A445+1 -> 2 | B446: ARGOLLA NÍQUEL 5 MM ZAMAC | C446: HERRAJES | D446: U | E446: 3356 | F446: U | G446: =IF(BD!$E445="","",(E446/(H446*I446))) -> 3356 | H446: 1 | I446: 1
A447: =A446+1 -> 3 | B447: ARGOLLA LLAVERO ORO 10 MM | C447: HERRAJES | D447: U | E447: 304.64 | F447: U | G447: =IF(BD!$E446="","",(E447/(H447*I447))) -> 304.64 | H447: 1 | I447: 1
A448: =A447+1 -> 4 | B448: ARGOLLA LLAVERO PAVÓN 1" | C448: HERRAJES | D448: U | E448: 304.64 | F448: U | G448: =IF(BD!$E447="","",(E448/(H448*I448))) -> 304.64 | H448: 1 | I448: 1
A449: =A448+1 -> 5 | B449: ARGOLLA LLAVERO PAVÓN 10 MM | C449: HERRAJES | D449: U | E449: 304.64 | F449: U | G449: =IF(BD!$E448="","",(E449/(H449*I449))) -> 304.64 | H449: 1 | I449: 1
A450: =A449+1 -> 6 | B450: ARGOLLA LLAVERO PLANO NÍQUEL 1" | C450: HERRAJES | D450: U | E450: 304.64 | F450: U | G450: =IF(BD!$E449="","",(E450/(H450*I450))) -> 304.64 | H450: 1 | I450: 1
A451: =A450+1 -> 7 | B451: ARGOLLA LLAVERO PLANO NÍQUEL 3/4" | C451: HERRAJES | D451: U | E451: 304.64 | F451: U | G451: =IF(BD!$E450="","",(E451/(H451*I451))) -> 304.64 | H451: 1 | I451: 1
A452: =A451+1 -> 8 | B452: ARGOLLA LLAVERO PLANO PAVÓN 1" | C452: HERRAJES | D452: U | E452: 304.64 | F452: U | G452: =IF(BD!$E451="","",(E452/(H452*I452))) -> 304.64 | H452: 1 | I452: 1
A453: =A452+1 -> 9 | B453: ARGOLLA LLAVERO PLANO PAVÓN 3/4" | C453: HERRAJES | D453: U | E453: 304.64 | F453: U | G453: =IF(BD!$E452="","",(E453/(H453*I453))) -> 304.64 | H453: 1 | I453: 1
A454: =A453+1 -> 10 | B454: ARGOLLA LLAVERO PLANO CON CADENA NÍQUEL 1" | C454: HERRAJES | D454: U | E454: 304.64 | F454: U | G454: =IF(BD!$E453="","",(E454/(H454*I454))) -> 304.64 | H454: 1 | I454: 1
A455: =A454+1 -> 11 | B455: ARGOLLA MOSQUETÓN | C455: HERRAJES | D455: U | E455: 2400 | F455: U | G455: =IF(BD!$E454="","",(E455/(H455*I455))) -> 2400 | H455: 1 | I455: 1
A456: =A455+1 -> 12 | B456: ARGOLLA MOSQUETÓN 1 1/4 F " | C456: HERRAJES | D456: U | E456: 2400 | F456: U | G456: =IF(BD!$E455="","",(E456/(H456*I456))) -> 2400 | H456: 1 | I456: 1
A457: =A456+1 -> 13 | B457: ARGOLLA MOSQUETÓN 1" | C457: HERRAJES | D457: U | E457: 2400 | F457: U | G457: =IF(BD!$E456="","",(E457/(H457*I457))) -> 2400 | H457: 1 | I457: 1
... A865: =A864+1 -> 421 | B865: UNIÓN CORREA METÁLICO 1/2" NÍQUEL | C865: HERRAJES | D865: U | E865: 1200 | F865: U | G865: =IF(BD!$E864="","",(E865/(H865*I865))) -> 1200 | H865: 1 | I865: 1
B890: Insertar Filas!!
A892: Totales | B892: =SUBTOTAL(3,(B894:B925)) -> 32
A893: Item | B893: Material | C893: Categoría | D893: Unidad de Compra Almacen | E893: Precio Unidad de Compra ( $) | F893: Unidad Despacho Almacen | G893: Valor /U Despacho en Almacen | H893: Magnitud 1 en U | I893: Magnitud 2 en U | J893: Columna1 | K893: Columna2
A894: 1 | B894: ARSENAL COLOR VERDE MILITAR | C894: SiNTETICOS_TEXTILES | D894: m | E894: 8770.3333 | F894: cm2 | G894: =IF(BD!$E894="","",(E894/(Tabla32[[#This Row],[Magnitud 1 en U]]*Tabla32[[#This Row],[Magnitud 2 en U]]))) -> 0.62645238 | H894: 140 | I894: 100
A895: =A894+1 -> 2 | B895: FORRO PIQUET | C895: SiNTETICOS_TEXTILES | D895: m | E895: 28016 | F895: cm2 | G895: =IF(BD!$E895="","",(E895/(Tabla32[[#This Row],[Magnitud 1 en U]]*Tabla32[[#This Row],[Magnitud 2 en U]]))) -> 2.0011429 | H895: 140 | I895: 100
A896: =A895+1 -> 3 | B896: FORRO MARROQUINERO DE POLIÉSTER | C896: SiNTETICOS_TEXTILES | D896: Rollo | E896: 28016 | F896: cm2 | G896: =IF(BD!$E896="","",(E896/(Tabla32[[#This Row],[Magnitud 1 en U]]*Tabla32[[#This Row],[Magnitud 2 en U]]))) -> 2.0011429 | H896: 140 | I896: 100
A897: =A896+1 -> 4 | B897: INTERLON | C897: SiNTETICOS_TEXTILES | D897: Rollo | E897: 10317 | F897: cm2 | G897: =IF(BD!$E897="","",(E897/(Tabla32[[#This Row],[Magnitud 1 en U]]*Tabla32[[#This Row],[Magnitud 2 en U]]))) -> 0.6878 | H897: 150 | I897: 100
A898: =A897+1 -> 5 | B898: LONA 600 | C898: SiNTETICOS_TEXTILES | D898: m | E898: 10200 | F898: cm2 | G898: =IF(BD!$E898="","",(E898/(Tabla32[[#This Row],[Magnitud 1 en U]]*Tabla32[[#This Row],[Magnitud 2 en U]]))) -> 0.72857143 | H898: 140 | I898: 100
A899: =A898+1 -> 6 | B899: LONA HURACAN LAFAYETTE | C899: SiNTETICOS_TEXTILES | D899: m | E899: 39999.47 | F899: cm2 | G899: =IF(BD!$E899="","",(E899/(Tabla32[[#This Row],[Magnitud 1 en U]]*Tabla32[[#This Row],[Magnitud 2 en U]]))) -> 2.857105 | H899: 140 | I899: 100
A900: =A899+1 -> 7 | B900: LONA LACOST | C900: SiNTETICOS_TEXTILES | D900: Rollo | E900: 10200 | F900: cm2 | G900: =IF(BD!$E900="","",(E900/(Tabla32[[#This Row],[Magnitud 1 en U]]*Tabla32[[#This Row],[Magnitud 2 en U]]))) -> 0.72857143 | H900: 140 | I900: 100
A901: =A900+1 -> 8 | B901: LONA PRELAVADA ALGODÓN | C901: SiNTETICOS_TEXTILES | D901: cm2 | E901: 28550 | F901: cm2 | G901: =IF(BD!$E901="","",(E901/(Tabla32[[#This Row],[Magnitud 1 en U]]*Tabla32[[#This Row],[Magnitud 2 en U]]))) -> 2.0392857 | H901: 140 | I901: 100
A902: =A901+1 -> 9 | B902: LONA REEBAG LAFAYETTE | C902: SiNTETICOS_TEXTILES | D902: m | E902: 34999.09 | F902: cm2 | G902: =IF(BD!$E902="","",(E902/(Tabla32[[#This Row],[Magnitud 1 en U]]*Tabla32[[#This Row],[Magnitud 2 en U]]))) -> 2.499935 | H902: 140 | I902: 100
A903: =A902+1 -> 10 | B903: LONA TEXTIL 2 | C903: SiNTETICOS_TEXTILES | D903: m | E903: 24999.52 | F903: cm2 | G903: =IF(BD!$E903="","",(E903/(Tabla32[[#This Row],[Magnitud 1 en U]]*Tabla32[[#This Row],[Magnitud 2 en U]]))) -> 1.78568 | H903: 140 | I903: 100
A904: =A903+1 -> 11 | B904: MALLA FABRICS | C904: SiNTETICOS_TEXTILES | D904: m | E904: 13269 | F904: cm2 | G904: =IF(BD!$E904="","",(E904/(Tabla32[[#This Row],[Magnitud 1 en U]]*Tabla32[[#This Row],[Magnitud 2 en U]]))) -> 0.94778571 | H904: 140 | I904: 100
A905: =A904+1 -> 12 | B905: MICROFIBRA BASE 0,5 Y 0,7 | C905: SiNTETICOS_TEXTILES | D905: m | E905: 20059.83 | F905: cm2 | G905: =IF(BD!$E905="","",(E905/(Tabla32[[#This Row],[Magnitud 1 en U]]*Tabla32[[#This Row],[Magnitud 2 en U]]))) -> 1.432845 | H905: 140 | I905: 100
A906: =A905+1 -> 13 | B906: MICROFIBRA DE SOPORTE SUAVE PARA CALZADO Y MARROQUINERÍA CALIBRE 0,3MM | C906: SiNTETICOS_TEXTILES | D906: m | E906: 31945 | F906: cm2 | G906: =IF(BD!$E906="","",(E906/(Tabla32[[#This Row],[Magnitud 1 en U]]*Tabla32[[#This Row],[Magnitud 2 en U]]))) -> 2.2817857 | H906: 140 | I906: 100
... A910: =A909+1 -> 17 | B910: NEOPRENO | C910: SiNTETICOS_TEXTILES | D910: m | E910: 34666.66 | F910: cm2 | G910: =IF(BD!$E910="","",(E910/(Tabla32[[#This Row],[Magnitud 1 en U]]*Tabla32[[#This Row],[Magnitud 2 en U]]))) -> 2.47619 | H910: 140 | I910: 100
A911: =A910+1 -> 18 | B911: POLITEX-KAMBREL 100 GR | C911: SiNTETICOS_TEXTILES | D911: cm2 | E911: 3550 | F911: cm2 | G911: =IF(BD!$E905="","",(E911/(Tabla32[[#This Row],[Magnitud 1 en U]]*Tabla32[[#This Row],[Magnitud 2 en U]]))) -> 0.23666667 | H911: 150 | I911: 100
A912: =A911+1 -> 19 | B912: SEDA ANTIFLUIDO, VARIOS COLORES | C912: SiNTETICOS_TEXTILES | D912: m | E912: 16591.6 | F912: cm2 | G912: =IF(BD!$E906="","",(E912/(Tabla32[[#This Row],[Magnitud 1 en U]]*Tabla32[[#This Row],[Magnitud 2 en U]]))) -> 1.1851143 | H912: 140 | I912: 100
A913: =A912+1 -> 20 | B913: SEDA AÑOS ANTERIORES | C913: SiNTETICOS_TEXTILES | D913: m | E913: 16813.51 | F913: cm2 | G913: =IF(BD!$E907="","",(E913/(Tabla32[[#This Row],[Magnitud 1 en U]]*Tabla32[[#This Row],[Magnitud 2 en U]]))) -> 1.200965 | H913: 140 | I913: 100
A914: =A913+1 -> 21 | B914: SEDA BRIDNI BASE LIVIANA X MT | C914: SiNTETICOS_TEXTILES | D914: m | E914: 19744.004 | F914: cm2 | G914: =IF(BD!$E908="","",(E914/(Tabla32[[#This Row],[Magnitud 1 en U]]*Tabla32[[#This Row],[Magnitud 2 en U]]))) -> 1.410286 | H914: 140 | I914: 100
A915: =A914+1 -> 22 | B915: SEDA CONOCIDA COMO: TIFON O 30-100 | C915: SiNTETICOS_TEXTILES | D915: m | E915: 9500 | F915: cm2 | G915: =IF(BD!$E909="","",(E915/(Tabla32[[#This Row],[Magnitud 1 en U]]*Tabla32[[#This Row],[Magnitud 2 en U]]))) -> 0.67857143 | H915: 140 | I915: 100
A916: =A915+1 -> 23 | B916: SEDA LACOST COLORES/VARIOS | C916: SiNTETICOS_TEXTILES | D916: m | E916: 7511.994 | F916: cm2 | G916: =IF(BD!$E910="","",(E916/(Tabla32[[#This Row],[Magnitud 1 en U]]*Tabla32[[#This Row],[Magnitud 2 en U]]))) -> 0.536571 | H916: 140 | I916: 100
A917: =A916+1 -> 24 | B917: SEDA LAFAYETTE VENDAVAL CON TECNOLOGIA LAFGARD | C917: SiNTETICOS_TEXTILES | D917: m | E917: 28016 | F917: cm2 | G917: =IF(BD!$E911="","",(E917/(Tabla32[[#This Row],[Magnitud 1 en U]]*Tabla32[[#This Row],[Magnitud 2 en U]]))) -> 2.0011429 | H917: 140 | I917: 100
A918: =A917+1 -> 25 | B918: SEDA POLIESTER | C918: SiNTETICOS_TEXTILES | D918: m | E918: 25200 | F918: cm2 | G918: =IF(BD!$E912="","",(E918/(Tabla32[[#This Row],[Magnitud 1 en U]]*Tabla32[[#This Row],[Magnitud 2 en U]]))) -> 1.8 | H918: 140 | I918: 100
A919: =A918+1 -> 26 | B919: SEDA TAFETA 100% POLIESTER | C919: SiNTETICOS_TEXTILES | D919: m | E919: 6970.59 | F919: cm2 | G919: =IF(BD!$E913="","",(E919/(Tabla32[[#This Row],[Magnitud 1 en U]]*Tabla32[[#This Row],[Magnitud 2 en U]]))) -> 0.49789929 | H919: 140 | I919: 100
A920: =A919+1 -> 27 | B920: SINTÉTICO P.U PARA CALZADO | C920: SiNTETICOS_TEXTILES | D920: m | E920: 44000 | F920: cm2 | G920: =IF(BD!$E915="","",(E920/(Tabla32[[#This Row],[Magnitud 1 en U]]*Tabla32[[#This Row],[Magnitud 2 en U]]))) -> 3.1428571 | H920: 140 | I920: 100
A921: =A920+1 -> 28 | B921: SINTETICO P.U PARA FORRO DE CALZADO | C921: SiNTETICOS_TEXTILES | D921: Rollo | E921: 18500 | F921: cm2 | G921: =IF(BD!$E916="","",(E921/(Tabla32[[#This Row],[Magnitud 1 en U]]*Tabla32[[#This Row],[Magnitud 2 en U]]))) -> 1.3214286 | H921: 140 | I921: 100
A922: =A921+1 -> 29 | B922: SINTETICO PVC | C922: SiNTETICOS_TEXTILES | D922: Rollo | E922: 39100 | F922: cm2 | G922: =IF(BD!$E917="","",(E922/(Tabla32[[#This Row],[Magnitud 1 en U]]*Tabla32[[#This Row],[Magnitud 2 en U]]))) -> 2.7928571 | H922: 140 | I922: 100
A923: =A922+1 -> 30 | B923: SUPER MALLA | C923: SiNTETICOS_TEXTILES | D923: Rollo | E923: 11950 | F923: cm2 | G923: =IF(BD!$E918="","",(E923/(Tabla32[[#This Row],[Magnitud 1 en U]]*Tabla32[[#This Row],[Magnitud 2 en U]]))) -> 0.85357143 | H923: 140 | I923: 100
A924: =A923+1 -> 31 | B924: TELA POLIESTER DE MALLA PIQUÉ, TERRY, MONZA, MALLA SANDWICH | C924: SiNTETICOS_TEXTILES | D924: m | E924: 5194 | F924: cm2 | G924: =IF(BD!$E919="","",(E924/(Tabla32[[#This Row],[Magnitud 1 en U]]*Tabla32[[#This Row],[Magnitud 2 en U]]))) -> 0.371 | H924: 140 | I924: 100
...

Sheet Listas
G1: Observaciones | I1: Categorias | V1: Lis
A2: Nombre de la Unidades | B2: Simbololo de la Unidad | G2: Restar_Pedido | I2: ADHESIVOS_Solventes
A3: Caja | B3: Caja | G3: Amarillo | I3: CUERO
A4: centimetros | B4: cm | G4: Azul | I4: HERRAJES
A5: centimetros cuadrados | B5: cm2 | G5: Blanco | I5: HERRAMIENTAS_
A6: Cono | B6: Cono | G6: Café | I6: INSUMOS_COMPL_
A7: decimetros | B7: dm | G7: Colores Surtidos | I7: SECUNDARIO
A8: decimetros Cuadrados | B8: dm2 | G8: Colores Varios | I8: SiNTETICOS_TEXTILES
A9: Frasco | B9: F | G9: Negro | I9: SUELAS
A10: Galon | B10: gal | G10: Rojo | I10: QUÍMICOS
A11: Garrafa | B11: gf | G11: Verde
A12: gramos | B12: g
A13: Hoja | B13: Hoja
A14: kilogramo | B14: kg
A15: kit | B15: kit
A16: Lamina | B16: Lámina
A17: Libra | B17: lb
A18: Litro | B18: l
A19: metros | B19: m
A20: miligramos | B20: mg
A21: mililitro | B21: ml
A22: Ovillo | B22: Ovillo
A23: Paquetre | B23: paq
... A28: Unidad | B28: U
